{
  "bivalence": "/bivalɑ̃s/",
  "bivalences": "/bivalɑ̃s/",
  "bivouac": "/bivwak/",
  "bivouacs": "/bivwak/",
  "bivouaqua": "/bivwaka/",
  "bivouaquai": "/bivwakɛ/",
  "bivouaquaient": "/bivwakɛ/",
  "bivouaquais": "/bivwakɛ/",
  "bivouaquait": "/bivwakɛ/",
  "bivouaquâmes": "/bivwakam/",
  "bivouaquant": "/bivwakɑ̃/",
  "bivouaquas": "/bivwaka/",
  "bivouaquasse": "/bivwakas/",
  "bivouaquassent": "/bivwakas/",
  "bivouaquasses": "/bivwakas/",
  "bivouaquassiez": "/bivwakasje/",
  "bivouaquassions": "/bivwakasjɔ̃/",
  "bivouaquât": "/bivwaka/",
  "bivouaquâtes": "/bivwakat/",
  "bivouaque": "/bivwak/",
  "bivouaqué": "/bivwake/",
  "bivouaquée": "/bivwake/",
  "bivouaquées": "/bivwake/",
  "bivouaquent": "/bivwak/",
  "bivouaquer": "/bivwake/",
  "bivouaquera": "/bivwakəʁa/",
  "bivouaquerai": "/bivwakəʁɛ/",
  "bivouaqueraient": "/bivwakəʁɛ/",
  "bivouaquerais": "/bivwakəʁɛ/",
  "bivouaquerait": "/bivwakəʁɛ/",
  "bivouaqueras": "/bivwakəʁa/",
  "bivouaquèrent": "/bivwakɛʁ/",
  "bivouaquerez": "/bivwakəʁe/",
  "bivouaqueriez": "/bivwakəʁje/",
  "bivouaquerions": "/bivwakəʁjɔ̃/",
  "bivouaquerons": "/bivwakəʁɔ̃/",
  "bivouaqueront": "/bivwakəʁɔ̃/",
  "bivouaques": "/bivwak/",
  "bivouaqués": "/bivwake/",
  "bivouaquez": "/bivwake/",
  "bivouaquiez": "/bivwakje/",
  "bivouaquions": "/bivwakjɔ̃/",
  "bivouaquons": "/bivwakɔ̃/"
}