{
  "car": "/kaʁ/",
  "car-ferry": "/kaʁfeʁi/",
  "carabin": "/kaʁabɛ̃/",
  "carabine": "/kaʁabin/",
  "carabiné": "/kaʁabine/",
  "carabinée": "/kaʁabine/",
  "carabinées": "/kaʁabine/",
  "carabines": "/kaʁabin/",
  "carabinés": "/kaʁabine/",
  "carabinier": "/kaʁabinje/",
  "carabiniers": "/kaʁabinje/",
  "carabins": "/kaʁabɛ̃/",
  "Carabosse": "/kaʁabɔs/",
  "Caracas": "/kaʁakas/",
  "caraco": "/kaʁako/",
  "caracola": "/kaʁakɔla/",
  "caracolai": "/kaʁakɔlɛ/",
  "caracolaient": "/kaʁakɔlɛ/",
  "caracolais": "/kaʁakɔlɛ/",
  "caracolait": "/kaʁakɔlɛ/",
  "caracolâmes": "/kaʁakɔlam/",
  "caracolant": "/kaʁakɔlɑ̃/",
  "caracolas": "/kaʁakɔla/",
  "caracolasse": "/kaʁakɔlas/",
  "caracolassent": "/kaʁakɔlas/",
  "caracolasses": "/kaʁakɔlas/",
  "caracolassiez": "/kaʁakɔlasje/",
  "caracolassions": "/kaʁakɔlasjɔ̃/",
  "caracolât": "/kaʁakɔla/",
  "caracolâtes": "/kaʁakɔlat/",
  "caracole": "/kaʁakɔl/",
  "caracolé": "/kaʁakɔle/",
  "caracolée": "/kaʁakɔle/",
  "caracolées": "/kaʁakɔle/",
  "caracolent": "/kaʁakɔl/",
  "caracoler": "/kaʁakɔle/",
  "caracolera": "/kaʁakɔləʁa/",
  "caracolerai": "/kaʁakɔləʁɛ/",
  "caracoleraient": "/kaʁakɔləʁɛ/",
  "caracolerais": "/kaʁakɔləʁɛ/",
  "caracolerait": "/kaʁakɔləʁɛ/",
  "caracoleras": "/kaʁakɔləʁa/",
  "caracolèrent": "/kaʁakɔlɛʁ/",
  "caracolerez": "/kaʁakɔləʁe/",
  "caracoleriez": "/kaʁakɔləʁje/",
  "caracolerions": "/kaʁakɔləʁjɔ̃/",
  "caracolerons": "/kaʁakɔləʁɔ̃/",
  "caracoleront": "/kaʁakɔləʁɔ̃/",
  "caracoles": "/kaʁakɔl/",
  "caracolés": "/kaʁakɔle/",
  "caracolez": "/kaʁakɔle/",
  "caracoliez": "/kaʁakɔlje/",
  "caracolions": "/kaʁakɔljɔ̃/",
  "caracolons": "/kaʁakɔlɔ̃/",
  "caracos": "/kaʁako/",
  "caractère": "/kaʁaktɛʁ/",
  "caractères": "/kaʁaktɛʁ/",
  "caractériel": "/kaʁakteʁjɛl/",
  "caractérielle": "/kaʁakteʁjɛl/",
  "caractérielles": "/kaʁakteʁjɛl/",
  "caractériels": "/kaʁakteʁjɛl/",
  "caractérisa": "/kaʁakteʁiza/",
  "caractérisai": "/kaʁakteʁizɛ/",
  "caractérisaient": "/kaʁakteʁizɛ/",
  "caractérisais": "/kaʁakteʁizɛ/",
  "caractérisait": "/kaʁakteʁizɛ/",
  "caractérisâmes": "/kaʁakteʁizam/",
  "caractérisant": "/kaʁakteʁizɑ̃/",
  "caractérisas": "/kaʁakteʁiza/",
  "caractérisasse": "/kaʁakteʁizas/",
  "caractérisassent": "/kaʁakteʁizas/",
  "caractérisasses": "/kaʁakteʁizas/",
  "caractérisassiez": "/kaʁakteʁizasje/",
  "caractérisassions": "/kaʁakteʁizasjɔ̃/",
  "caractérisât": "/kaʁakteʁiza/",
  "caractérisâtes": "/kaʁakteʁizat/",
  "caractérisation": "/kaʁakteʁizasjɔ̃/",
  "caractérisations": "/kaʁakteʁizasjɔ̃/",
  "caractérise": "/kaʁakteʁiz/",
  "caractérisé": "/kaʁakteʁize/",
  "caractérisée": "/kaʁakteʁize/",
  "caractérisées": "/kaʁakteʁize/",
  "caractérisent": "/kaʁakteʁiz/",
  "caractériser": "/kaʁakteʁize/",
  "caractérisera": "/kaʁakteʁizəʁa/",
  "caractériserai": "/kaʁakteʁizəʁɛ/",
  "caractériseraient": "/kaʁakteʁizəʁɛ/",
  "caractériserais": "/kaʁakteʁizəʁɛ/",
  "caractériserait": "/kaʁakteʁizəʁɛ/",
  "caractériseras": "/kaʁakteʁizəʁa/",
  "caractérisèrent": "/kaʁakteʁizɛʁ/",
  "caractériserez": "/kaʁakteʁizəʁe/",
  "caractériseriez": "/kaʁakteʁizəʁje/",
  "caractériserions": "/kaʁakteʁizəʁjɔ̃/",
  "caractériserons": "/kaʁakteʁizəʁɔ̃/",
  "caractériseront": "/kaʁakteʁizəʁɔ̃/",
  "caractérises": "/kaʁakteʁiz/",
  "caractérisés": "/kaʁakteʁize/",
  "caractérisez": "/kaʁakteʁize/",
  "caractérisiez": "/kaʁakteʁizje/",
  "caractérisions": "/kaʁakteʁizjɔ̃/",
  "caractérisons": "/kaʁakteʁizɔ̃/",
  "caractéristique": "/kaʁakteʁistik/",
  "caractéristiques": "/kaʁakteʁistik/",
  "caractérologie": "/kaʁakteʁɔlɔʒi/",
  "caractérologies": "/kaʁakteʁɔlɔʒi/",
  "carafe": "/kaʁaf/",
  "carafes": "/kaʁaf/",
  "carafon": "/kaʁafɔ̃/",
  "carafons": "/kaʁafɔ̃/",
  "caraïbe": "/kaʁaib/",
  "Caraïbe": "/kaʁaib/",
  "caraïbes": "/kaʁaib/",
  "Caraïbes": "/kaʁaib/",
  "carambola": "/kaʁɑ̃bɔla/",
  "carambolage": "/kaʁɑ̃bɔlaʒ/",
  "carambolages": "/kaʁɑ̃bɔlaʒ/",
  "carambolai": "/kaʁɑ̃bɔlɛ/",
  "carambolaient": "/kaʁɑ̃bɔlɛ/",
  "carambolais": "/kaʁɑ̃bɔlɛ/",
  "carambolait": "/kaʁɑ̃bɔlɛ/",
  "carambolâmes": "/kaʁɑ̃bɔlam/",
  "carambolant": "/kaʁɑ̃bɔlɑ̃/",
  "carambolas": "/kaʁɑ̃bɔla/",
  "carambolasse": "/kaʁɑ̃bɔlas/",
  "carambolassent": "/kaʁɑ̃bɔlas/",
  "carambolasses": "/kaʁɑ̃bɔlas/",
  "carambolassiez": "/kaʁɑ̃bɔlasje/",
  "carambolassions": "/kaʁɑ̃bɔlasjɔ̃/",
  "carambolât": "/kaʁɑ̃bɔla/",
  "carambolâtes": "/kaʁɑ̃bɔlat/",
  "carambole": "/kaʁɑ̃bɔl/",
  "carambolé": "/kaʁɑ̃bɔle/",
  "carambolée": "/kaʁɑ̃bɔle/",
  "carambolées": "/kaʁɑ̃bɔle/",
  "carambolent": "/kaʁɑ̃bɔl/",
  "caramboler": "/kaʁɑ̃bɔle/",
  "carambolera": "/kaʁɑ̃bɔləʁa/",
  "carambolerai": "/kaʁɑ̃bɔləʁɛ/",
  "caramboleraient": "/kaʁɑ̃bɔləʁɛ/",
  "carambolerais": "/kaʁɑ̃bɔləʁɛ/",
  "carambolerait": "/kaʁɑ̃bɔləʁɛ/",
  "caramboleras": "/kaʁɑ̃bɔləʁa/",
  "carambolèrent": "/kaʁɑ̃bɔlɛʁ/",
  "carambolerez": "/kaʁɑ̃bɔləʁe/",
  "caramboleriez": "/kaʁɑ̃bɔləʁje/",
  "carambolerions": "/kaʁɑ̃bɔləʁjɔ̃/",
  "carambolerons": "/kaʁɑ̃bɔləʁɔ̃/",
  "caramboleront": "/kaʁɑ̃bɔləʁɔ̃/",
  "caramboles": "/kaʁɑ̃bɔl/",
  "carambolés": "/kaʁɑ̃bɔle/",
  "carambolez": "/kaʁɑ̃bɔle/",
  "caramboliez": "/kaʁɑ̃bɔlje/",
  "carambolions": "/kaʁɑ̃bɔljɔ̃/",
  "carambolons": "/kaʁɑ̃bɔlɔ̃/",
  "carambouillage": "/kaʁɑ̃bujaʒ/",
  "carambouillages": "/kaʁɑ̃bujaʒ/",
  "caramel": "/kaʁamɛl/",
  "caramélisa": "/kaʁameliza/",
  "caramélisai": "/kaʁamelizɛ/",
  "caramélisaient": "/kaʁamelizɛ/",
  "caramélisais": "/kaʁamelizɛ/",
  "caramélisait": "/kaʁamelizɛ/",
  "caramélisâmes": "/kaʁamelizam/",
  "caramélisant": "/kaʁamelizɑ̃/",
  "caramélisas": "/kaʁameliza/",
  "caramélisasse": "/kaʁamelizas/",
  "caramélisassent": "/kaʁamelizas/",
  "caramélisasses": "/kaʁamelizas/",
  "caramélisassiez": "/kaʁamelizasje/",
  "caramélisassions": "/kaʁamelizasjɔ̃/",
  "caramélisât": "/kaʁameliza/",
  "caramélisâtes": "/kaʁamelizat/",
  "caramélise": "/kaʁameliz/",
  "caramélisé": "/kaʁamelize/",
  "caramélisée": "/kaʁamelize/",
  "caramélisées": "/kaʁamelize/",
  "caramélisent": "/kaʁameliz/",
  "caraméliser": "/kaʁamelize/",
  "caramélisera": "/kaʁamelizəʁa/",
  "caraméliserai": "/kaʁamelizəʁɛ/",
  "caraméliseraient": "/kaʁamelizəʁɛ/",
  "caraméliserais": "/kaʁamelizəʁɛ/",
  "caraméliserait": "/kaʁamelizəʁɛ/",
  "caraméliseras": "/kaʁamelizəʁa/",
  "caramélisèrent": "/kaʁamelizɛʁ/",
  "caraméliserez": "/kaʁamelizəʁe/",
  "caraméliseriez": "/kaʁamelizəʁje/",
  "caraméliserions": "/kaʁamelizəʁjɔ̃/",
  "caraméliserons": "/kaʁamelizəʁɔ̃/",
  "caraméliseront": "/kaʁamelizəʁɔ̃/",
  "caramélises": "/kaʁameliz/",
  "caramélisés": "/kaʁamelize/",
  "caramélisez": "/kaʁamelize/",
  "caramélisiez": "/kaʁamelizje/",
  "caramélisions": "/kaʁamelizjɔ̃/",
  "caramélisons": "/kaʁamelizɔ̃/",
  "caramels": "/kaʁamɛl/",
  "carapace": "/kaʁapas/",
  "carapaces": "/kaʁapas/",
  "carapata": "/kaʁapata/",
  "carapatai": "/kaʁapatɛ/",
  "carapataient": "/kaʁapatɛ/",
  "carapatais": "/kaʁapatɛ/",
  "carapatait": "/kaʁapatɛ/",
  "carapatâmes": "/kaʁapatam/",
  "carapatant": "/kaʁapatɑ̃/",
  "carapatas": "/kaʁapata/",
  "carapatasse": "/kaʁapatas/",
  "carapatassent": "/kaʁapatas/",
  "carapatasses": "/kaʁapatas/",
  "carapatassiez": "/kaʁapatasje/",
  "carapatassions": "/kaʁapatasjɔ̃/",
  "carapatât": "/kaʁapata/",
  "carapatâtes": "/kaʁapatat/",
  "carapate": "/kaʁapat/",
  "carapaté": "/kaʁapate/",
  "carapatée": "/kaʁapate/",
  "carapatées": "/kaʁapate/",
  "carapatent": "/kaʁapat/",
  "carapater": "/kaʁapate/",
  "carapatera": "/kaʁapatəʁa/",
  "carapaterai": "/kaʁapatəʁɛ/",
  "carapateraient": "/kaʁapatəʁɛ/",
  "carapaterais": "/kaʁapatəʁɛ/",
  "carapaterait": "/kaʁapatəʁɛ/",
  "carapateras": "/kaʁapatəʁa/",
  "carapatèrent": "/kaʁapatɛʁ/",
  "carapaterez": "/kaʁapatəʁe/",
  "carapateriez": "/kaʁapatəʁje/",
  "carapaterions": "/kaʁapatəʁjɔ̃/",
  "carapaterons": "/kaʁapatəʁɔ̃/",
  "carapateront": "/kaʁapatəʁɔ̃/",
  "carapates": "/kaʁapat/",
  "carapatés": "/kaʁapate/",
  "carapatez": "/kaʁapate/",
  "carapatiez": "/kaʁapatje/",
  "carapations": "/kaʁapatjɔ̃/",
  "carapatons": "/kaʁapatɔ̃/",
  "carat": "/kaʁa/",
  "carats": "/kaʁa/",
  "Caravage": "/kaʁavaʒ/",
  "caravanage": "/kaʁavanaʒ/",
  "caravanages": "/kaʁavanaʒ/",
  "caravane": "/kaʁavan/",
  "caravanes": "/kaʁavan/",
  "caravanier": "/kaʁavanje/",
  "caravanière": "/kaʁavanjɛʁ/",
  "caravanières": "/kaʁavanjɛʁ/",
  "caravaniers": "/kaʁavanje/",
  "caravaning": "/kaʁavaniŋ/",
  "caravansérail": "/kaʁavɑ̃seʁaj/",
  "caravansérails": "/kaʁavɑ̃seʁaj/",
  "caravelle": "/kaʁavɛl/",
  "Caravelle": "/kaʁavɛl/",
  "caravelles": "/kaʁavɛl/",
  "carbonade": "/kaʁbɔnad/",
  "carbonate": "/kaʁbɔnat/",
  "carbonates": "/kaʁbɔnat/",
  "carbone": "/kaʁbɔn/",
  "carboné": "/kaʁbɔne/",
  "carbonée": "/kaʁbɔne/",
  "carbonées": "/kaʁbɔne/",
  "carbones": "/kaʁbɔn/",
  "carbonés": "/kaʁbɔne/",
  "carbonique": "/kaʁbɔnik/",
  "carboniques": "/kaʁbɔnik/",
  "carbonisa": "/kaʁbɔniza/",
  "carbonisai": "/kaʁbɔnizɛ/",
  "carbonisaient": "/kaʁbɔnizɛ/",
  "carbonisais": "/kaʁbɔnizɛ/",
  "carbonisait": "/kaʁbɔnizɛ/",
  "carbonisâmes": "/kaʁbɔnizam/",
  "carbonisant": "/kaʁbɔnizɑ̃/",
  "carbonisas": "/kaʁbɔniza/",
  "carbonisasse": "/kaʁbɔnizas/",
  "carbonisassent": "/kaʁbɔnizas/",
  "carbonisasses": "/kaʁbɔnizas/",
  "carbonisassiez": "/kaʁbɔnizasje/",
  "carbonisassions": "/kaʁbɔnizasjɔ̃/",
  "carbonisât": "/kaʁbɔniza/",
  "carbonisâtes": "/kaʁbɔnizat/",
  "carbonise": "/kaʁbɔniz/",
  "carbonisé": "/kaʁbɔnize/",
  "carbonisée": "/kaʁbɔnize/",
  "carbonisées": "/kaʁbɔnize/",
  "carbonisent": "/kaʁbɔniz/",
  "carboniser": "/kaʁbɔnize/",
  "carbonisera": "/kaʁbɔnizəʁa/",
  "carboniserai": "/kaʁbɔnizəʁɛ/",
  "carboniseraient": "/kaʁbɔnizəʁɛ/",
  "carboniserais": "/kaʁbɔnizəʁɛ/",
  "carboniserait": "/kaʁbɔnizəʁɛ/",
  "carboniseras": "/kaʁbɔnizəʁa/",
  "carbonisèrent": "/kaʁbɔnizɛʁ/",
  "carboniserez": "/kaʁbɔnizəʁe/",
  "carboniseriez": "/kaʁbɔnizəʁje/",
  "carboniserions": "/kaʁbɔnizəʁjɔ̃/",
  "carboniserons": "/kaʁbɔnizəʁɔ̃/",
  "carboniseront": "/kaʁbɔnizəʁɔ̃/",
  "carbonises": "/kaʁbɔniz/",
  "carbonisés": "/kaʁbɔnize/",
  "carbonisez": "/kaʁbɔnize/",
  "carbonisiez": "/kaʁbɔnizje/",
  "carbonisions": "/kaʁbɔnizjɔ̃/",
  "carbonisons": "/kaʁbɔnizɔ̃/",
  "carbonnade": "/kaʁbɔnad/",
  "carbonnades": "/kaʁbɔnad/",
  "carbura": "/kaʁbyʁa/",
  "carburai": "/kaʁbyʁɛ/",
  "carburaient": "/kaʁbyʁɛ/",
  "carburais": "/kaʁbyʁɛ/",
  "carburait": "/kaʁbyʁɛ/",
  "carburâmes": "/kaʁbyʁam/",
  "carburant": "/kaʁbyʁɑ̃/",
  "carburants": "/kaʁbyʁɑ̃/",
  "carburas": "/kaʁbyʁa/",
  "carburasse": "/kaʁbyʁas/",
  "carburassent": "/kaʁbyʁas/",
  "carburasses": "/kaʁbyʁas/",
  "carburassiez": "/kaʁbyʁasje/",
  "carburassions": "/kaʁbyʁasjɔ̃/",
  "carburât": "/kaʁbyʁa/",
  "carburâtes": "/kaʁbyʁat/",
  "carburateur": "/kaʁbyʁatœʁ/",
  "carburateurs": "/kaʁbyʁatœʁ/",
  "carburation": "/kaʁbyʁasjɔ̃/",
  "carburations": "/kaʁbyʁasjɔ̃/",
  "carbure": "/kaʁbyʁ/",
  "carburé": "/kaʁbyʁe/",
  "carburée": "/kaʁbyʁe/",
  "carburées": "/kaʁbyʁe/",
  "carburent": "/kaʁbyʁ/",
  "carburer": "/kaʁbyʁe/",
  "carburera": "/kaʁbyʁəʁa/",
  "carburerai": "/kaʁbyʁəʁɛ/",
  "carbureraient": "/kaʁbyʁəʁɛ/",
  "carburerais": "/kaʁbyʁəʁɛ/",
  "carburerait": "/kaʁbyʁəʁɛ/",
  "carbureras": "/kaʁbyʁəʁa/",
  "carburèrent": "/kaʁbyʁɛʁ/",
  "carburerez": "/kaʁbyʁəʁe/",
  "carbureriez": "/kaʁbyʁəʁje/",
  "carburerions": "/kaʁbyʁəʁjɔ̃/",
  "carburerons": "/kaʁbyʁəʁɔ̃/",
  "carbureront": "/kaʁbyʁəʁɔ̃/",
  "carbures": "/kaʁbyʁ/",
  "carburés": "/kaʁbyʁe/",
  "carburez": "/kaʁbyʁe/",
  "carburiez": "/kaʁbyʁje/",
  "carburions": "/kaʁbyʁjɔ̃/",
  "carburons": "/kaʁbyʁɔ̃/",
  "carcan": "/kaʁkɑ̃/",
  "carcans": "/kaʁkɑ̃/",
  "carcasse": "/kaʁkas/",
  "carcasses": "/kaʁkas/",
  "carcéral": "/kaʁseʁal/",
  "carcérale": "/kaʁseʁal/",
  "carcérales": "/kaʁseʁal/",
  "carcéraux": "/kaʁseʁo/",
  "carcinome": "/kaʁsinom/",
  "carcinomes": "/kaʁsinom/",
  "carda": "/kaʁda/",
  "cardage": "/kaʁdaʒ/",
  "cardages": "/kaʁdaʒ/",
  "cardai": "/kaʁdɛ/",
  "cardaient": "/kaʁdɛ/",
  "cardais": "/kaʁdɛ/",
  "cardait": "/kaʁdɛ/",
  "cardâmes": "/kaʁdam/",
  "cardan": "/kaʁdɑ̃/",
  "cardans": "/kaʁdɑ̃/",
  "cardant": "/kaʁdɑ̃/",
  "cardas": "/kaʁda/",
  "cardasse": "/kaʁdas/",
  "cardassent": "/kaʁdas/",
  "cardasses": "/kaʁdas/",
  "cardassiez": "/kaʁdasje/",
  "cardassions": "/kaʁdasjɔ̃/",
  "cardât": "/kaʁda/",
  "cardâtes": "/kaʁdat/",
  "carde": "/kaʁd/",
  "cardé": "/kaʁde/",
  "cardée": "/kaʁde/",
  "cardées": "/kaʁde/",
  "cardent": "/kaʁd/",
  "carder": "/kaʁde/",
  "cardera": "/kaʁdəʁa/",
  "carderai": "/kaʁdəʁɛ/",
  "carderaient": "/kaʁdəʁɛ/",
  "carderais": "/kaʁdəʁɛ/",
  "carderait": "/kaʁdəʁɛ/",
  "carderas": "/kaʁdəʁa/",
  "cardère": "/kaʁdɛʁ/",
  "cardèrent": "/kaʁdɛʁ/",
  "cardères": "/kaʁdɛʁ/",
  "carderez": "/kaʁdəʁe/",
  "carderiez": "/kaʁdəʁje/",
  "carderions": "/kaʁdəʁjɔ̃/",
  "carderons": "/kaʁdəʁɔ̃/",
  "carderont": "/kaʁdəʁɔ̃/",
  "cardes": "/kaʁd/",
  "cardés": "/kaʁde/",
  "cardeur": "/kaʁdœʁ/",
  "cardeurs": "/kaʁdœʁ/",
  "cardeuse": "/kaʁdøz/",
  "cardeuses": "/kaʁdøz/",
  "cardez": "/kaʁde/",
  "cardiaque": "/kaʁdjak/",
  "cardiaques": "/kaʁdjak/",
  "cardiez": "/kaʁdje/",
  "cardigan": "/kaʁdigɑ̃/",
  "cardigans": "/kaʁdigɑ̃/",
  "cardinal": "/kaʁdinal/",
  "cardinale": "/kaʁdinal/",
  "cardinales": "/kaʁdinal/",
  "cardinaux": "/kaʁdino/",
  "cardio-pulmonaire": "/kaʁdjopylmɔnɛʁ/",
  "cardio-respiratoire": "/kaʁdjoʁɛspiʁatwaʁ/",
  "cardio-training": "/kaʁdjotʁɛniŋ/",
  "cardio-vasculaire": "/kaʁdjovaskylɛʁ/",
  "cardio-vasculaires": "/kaʁdjovaskylɛʁ/",
  "cardiogramme": "/kaʁdjogʁam/",
  "cardiogrammes": "/kaʁdjogʁam/",
  "cardiographie": "/kaʁdjogʁafi/",
  "cardiologie": "/kaʁdjolɔʒi/",
  "cardiologies": "/kaʁdjolɔʒi/",
  "cardiologue": "/kaʁdjolɔg/",
  "cardiologues": "/kaʁdjolɔg/",
  "cardiomyopathie": "/kaʁdjomjɔpati/",
  "cardions": "/kaʁdjɔ̃/",
  "cardiopathie": "/kaʁdjopati/",
  "cardiopathies": "/kaʁdjopati/",
  "cardon": "/kaʁdɔ̃/",
  "cardons": "/kaʁdɔ̃/",
  "carême": "/kaʁɛm/",
  "carêmes": "/kaʁɛm/",
  "caréna": "/kaʁena/",
  "carénage": "/kaʁenaʒ/",
  "carénages": "/kaʁenaʒ/",
  "carénai": "/kaʁenɛ/",
  "carénaient": "/kaʁenɛ/",
  "carénais": "/kaʁenɛ/",
  "carénait": "/kaʁenɛ/",
  "carénâmes": "/kaʁenɑm/",
  "carénant": "/kaʁenɑ̃/",
  "carénas": "/kaʁena/",
  "carénasse": "/kaʁenas/",
  "carénassent": "/kaʁenas/",
  "carénasses": "/kaʁenas/",
  "carénassiez": "/kaʁenasje/",
  "carénassions": "/kaʁenasjɔ̃/",
  "carénât": "/kaʁenɑ/",
  "carénâtes": "/kaʁenɑt/",
  "carença": "/kaʁɑ̃sa/",
  "carençai": "/kaʁɑ̃sɛ/",
  "carençaient": "/kaʁɑ̃sɛ/",
  "carençais": "/kaʁɑ̃sɛ/",
  "carençait": "/kaʁɑ̃sɛ/",
  "carençâmes": "/kaʁɑ̃sɑm/",
  "carençant": "/kaʁɑ̃sɑ̃/",
  "carenças": "/kaʁɑ̃sa/",
  "carençasse": "/kaʁɑ̃sas/",
  "carençassent": "/kaʁɑ̃sas/",
  "carençasses": "/kaʁɑ̃sas/",
  "carençassiez": "/kaʁɑ̃sasje/",
  "carençassions": "/kaʁɑ̃sasjɔ̃/",
  "carençât": "/kaʁɑ̃sɑ/",
  "carençâtes": "/kaʁɑ̃sɑt/",
  "carence": "/kaʁɑ̃s/",
  "carencé": "/kaʁɑ̃se/",
  "carencée": "/kaʁɑ̃se/",
  "carencées": "/kaʁɑ̃se/",
  "carencent": "/kaʁɑ̃s/",
  "carencer": "/kaʁɑ̃se/",
  "carencera": "/kaʁɑ̃səʁa/",
  "carencerai": "/kaʁɑ̃səʁɛ/",
  "carenceraient": "/kaʁɑ̃səʁɛ/",
  "carencerais": "/kaʁɑ̃səʁɛ/",
  "carencerait": "/kaʁɑ̃səʁɛ/",
  "carenceras": "/kaʁɑ̃səʁa/",
  "carencèrent": "/kaʁɑ̃sɛʁ/",
  "carencerez": "/kaʁɑ̃səʁe/",
  "carenceriez": "/kaʁɑ̃səʁje/",
  "carencerions": "/kaʁɑ̃səʁjɔ̃/",
  "carencerons": "/kaʁɑ̃səʁɔ̃/",
  "carenceront": "/kaʁɑ̃səʁɔ̃/",
  "carences": "/kaʁɑ̃s/",
  "carencés": "/kaʁɑ̃se/",
  "carencez": "/kaʁɑ̃se/",
  "carenciez": "/kaʁɑ̃sje/",
  "carencions": "/kaʁɑ̃sjɔ̃/",
  "carençons": "/kaʁɑ̃sɔ̃/",
  "caréné": "/kaʁene/",
  "carène": "/kaʁɛn/",
  "carénée": "/kaʁene/",
  "carénées": "/kaʁene/",
  "carènent": "/kaʁɛn/",
  "caréner": "/kaʁene/",
  "carénera": "/kaʁenəʁa/",
  "carènera": "/kaʁɛnəʁa/",
  "carénerai": "/kaʁenəʁɛ/",
  "carènerai": "/kaʁɛnəʁɛ/",
  "caréneraient": "/kaʁenəʁɛ/",
  "carèneraient": "/kaʁɛnəʁɛ/",
  "carénerais": "/kaʁenəʁɛ/",
  "carènerais": "/kaʁɛnəʁɛ/",
  "carénerait": "/kaʁenəʁɛ/",
  "carènerait": "/kaʁɛnəʁɛ/",
  "caréneras": "/kaʁenəʁa/",
  "carèneras": "/kaʁɛnəʁa/",
  "carénèrent": "/kaʁenɛʁ/",
  "carénerez": "/kaʁenəʁe/",
  "carènerez": "/kaʁɛnəʁe/",
  "caréneriez": "/kaʁenəʁje/",
  "carèneriez": "/kaʁɛnəʁje/",
  "carénerions": "/kaʁenəʁjɔ̃/",
  "carènerions": "/kaʁɛnəʁjɔ̃/",
  "carénerons": "/kaʁenəʁɔ̃/",
  "carènerons": "/kaʁɛnəʁɔ̃/",
  "caréneront": "/kaʁenəʁɔ̃/",
  "carèneront": "/kaʁɛnəʁɔ̃/",
  "carénés": "/kaʁene/",
  "carènes": "/kaʁɛn/",
  "carénez": "/kaʁene/",
  "caréniez": "/kaʁenje/",
  "carénions": "/kaʁenjɔ̃/",
  "carénons": "/kaʁenɔ̃/",
  "carentiel": "/kaʁɑ̃sjɛl/",
  "carentielle": "/kaʁɑ̃sjɛl/",
  "carentielles": "/kaʁɑ̃sjɛl/",
  "carentiels": "/kaʁɑ̃sjɛl/",
  "caressa": "/kaʁɛsa/",
  "caressai": "/kaʁɛsɛ/",
  "caressaient": "/kaʁɛsɛ/",
  "caressais": "/kaʁɛsɛ/",
  "caressait": "/kaʁɛsɛ/",
  "caressâmes": "/kaʁɛsam/",
  "caressant": "/kaʁɛsɑ̃/",
  "caressante": "/kaʁɛsɑ̃t/",
  "caressantes": "/kaʁɛsɑ̃t/",
  "caressants": "/kaʁɛsɑ̃/",
  "caressas": "/kaʁɛsa/",
  "caressasse": "/kaʁɛsas/",
  "caressassent": "/kaʁɛsas/",
  "caressasses": "/kaʁɛsas/",
  "caressassiez": "/kaʁɛsasje/",
  "caressassions": "/kaʁɛsasjɔ̃/",
  "caressât": "/kaʁɛsa/",
  "caressâtes": "/kaʁɛsat/",
  "caresse": "/kaʁɛs/",
  "caressé": "/kaʁɛse/",
  "caressée": "/kaʁɛse/",
  "caressées": "/kaʁɛse/",
  "caressent": "/kaʁɛs/",
  "caresser": "/kaʁɛse/, /kaʁese/",
  "caressera": "/kaʁɛsəʁa/",
  "caresserai": "/kaʁɛsəʁɛ/",
  "caresseraient": "/kaʁɛsəʁɛ/",
  "caresserais": "/kaʁɛsəʁɛ/",
  "caresserait": "/kaʁɛsəʁɛ/",
  "caresseras": "/kaʁɛsəʁa/",
  "caressèrent": "/kaʁɛsɛʁ/",
  "caresserez": "/kaʁɛsəʁe/",
  "caresseriez": "/kaʁɛsəʁje/",
  "caresserions": "/kaʁɛsəʁjɔ̃/",
  "caresserons": "/kaʁɛsəʁɔ̃/",
  "caresseront": "/kaʁɛsəʁɔ̃/",
  "caresses": "/kaʁɛs/",
  "caressés": "/kaʁɛse/",
  "caressez": "/kaʁɛse/",
  "caressiez": "/kaʁɛsje/",
  "caressions": "/kaʁɛsjɔ̃/",
  "caressons": "/kaʁɛsɔ̃/",
  "cargaison": "/kaʁgɛzɔ̃/",
  "cargaisons": "/kaʁgɛzɔ̃/",
  "cargo": "/kaʁgo/",
  "cargos": "/kaʁgo/",
  "cari": "/kaʁi/",
  "caria": "/kaʁja/",
  "cariai": "/kaʁjɛ/",
  "cariaient": "/kaʁjɛ/",
  "cariais": "/kaʁjɛ/",
  "cariait": "/kaʁjɛ/",
  "cariâmes": "/kaʁjam/",
  "cariant": "/kaʁjɑ̃/",
  "carias": "/kaʁja/",
  "cariasse": "/kaʁjas/",
  "cariassent": "/kaʁjas/",
  "cariasses": "/kaʁjas/",
  "cariassiez": "/kaʁjasje/",
  "cariassions": "/kaʁjasjɔ̃/",
  "cariât": "/kaʁja/",
  "cariâtes": "/kaʁjat/",
  "cariatide": "/kaʁjatid/",
  "cariatides": "/kaʁjatid/",
  "caribou": "/kaʁibu/",
  "caribous": "/kaʁibu/",
  "caricatura": "/kaʁikatyʁa/",
  "caricaturai": "/kaʁikatyʁɛ/",
  "caricaturaient": "/kaʁikatyʁɛ/",
  "caricaturais": "/kaʁikatyʁɛ/",
  "caricaturait": "/kaʁikatyʁɛ/",
  "caricatural": "/kaʁikatyʁal/",
  "caricaturale": "/kaʁikatyʁal/",
  "caricaturales": "/kaʁikatyʁal/",
  "caricaturâmes": "/kaʁikatyʁam/",
  "caricaturant": "/kaʁikatyʁɑ̃/",
  "caricaturas": "/kaʁikatyʁa/",
  "caricaturasse": "/kaʁikatyʁas/",
  "caricaturassent": "/kaʁikatyʁas/",
  "caricaturasses": "/kaʁikatyʁas/",
  "caricaturassiez": "/kaʁikatyʁasje/",
  "caricaturassions": "/kaʁikatyʁasjɔ̃/",
  "caricaturât": "/kaʁikatyʁa/",
  "caricaturâtes": "/kaʁikatyʁat/",
  "caricaturaux": "/kaʁikatyʁo/",
  "caricature": "/kaʁikatyʁ/",
  "caricaturé": "/kaʁikatyʁe/",
  "caricaturée": "/kaʁikatyʁe/",
  "caricaturées": "/kaʁikatyʁe/",
  "caricaturent": "/kaʁikatyʁ/",
  "caricaturer": "/kaʁikatyʁe/",
  "caricaturera": "/kaʁikatyʁəʁa/",
  "caricaturerai": "/kaʁikatyʁəʁɛ/",
  "caricatureraient": "/kaʁikatyʁəʁɛ/",
  "caricaturerais": "/kaʁikatyʁəʁɛ/",
  "caricaturerait": "/kaʁikatyʁəʁɛ/",
  "caricatureras": "/kaʁikatyʁəʁa/",
  "caricaturèrent": "/kaʁikatyʁɛʁ/",
  "caricaturerez": "/kaʁikatyʁəʁe/",
  "caricatureriez": "/kaʁikatyʁəʁje/",
  "caricaturerions": "/kaʁikatyʁəʁjɔ̃/",
  "caricaturerons": "/kaʁikatyʁəʁɔ̃/",
  "caricatureront": "/kaʁikatyʁəʁɔ̃/",
  "caricatures": "/kaʁikatyʁ/",
  "caricaturés": "/kaʁikatyʁe/",
  "caricaturez": "/kaʁikatyʁe/",
  "caricaturiez": "/kaʁikatyʁje/",
  "caricaturions": "/kaʁikatyʁjɔ̃/",
  "caricaturiste": "/kaʁikatyʁist/",
  "caricaturistes": "/kaʁikatyʁist/",
  "caricaturons": "/kaʁikatyʁɔ̃/",
  "carie": "/kaʁi/",
  "carié": "/kaʁje/",
  "cariée": "/kaʁje/",
  "cariées": "/kaʁje/",
  "carient": "/kaʁi/",
  "carier": "/kaʁje/",
  "cariera": "/kaʁjəʁa/",
  "carierai": "/kaʁjəʁɛ/",
  "carieraient": "/kaʁjəʁɛ/",
  "carierais": "/kaʁjəʁɛ/",
  "carierait": "/kaʁjəʁɛ/",
  "carieras": "/kaʁjəʁa/",
  "carièrent": "/kaʁjɛʁ/",
  "carierez": "/kaʁjəʁe/",
  "carieriez": "/kaʁjəʁje/",
  "carierions": "/kaʁjəʁjɔ̃/",
  "carierons": "/kaʁjəʁɔ̃/",
  "carieront": "/kaʁjəʁɔ̃/",
  "caries": "/kaʁi/",
  "cariés": "/kaʁje/",
  "cariez": "/kaʁje/",
  "cariiez": "/kaʁije/",
  "cariions": "/kaʁijɔ̃/",
  "carillon": "/kaʁijɔ̃/",
  "carillonna": "/kaʁijɔna/",
  "carillonnai": "/kaʁijɔnɛ/",
  "carillonnaient": "/kaʁijɔnɛ/",
  "carillonnais": "/kaʁijɔnɛ/",
  "carillonnait": "/kaʁijɔnɛ/",
  "carillonnâmes": "/kaʁijɔnam/",
  "carillonnant": "/kaʁijɔnɑ̃/",
  "carillonnas": "/kaʁijɔna/",
  "carillonnasse": "/kaʁijɔnas/",
  "carillonnassent": "/kaʁijɔnas/",
  "carillonnasses": "/kaʁijɔnas/",
  "carillonnassiez": "/kaʁijɔnasje/",
  "carillonnassions": "/kaʁijɔnasjɔ̃/",
  "carillonnât": "/kaʁijɔna/",
  "carillonnâtes": "/kaʁijɔnat/",
  "carillonne": "/kaʁijɔn/",
  "carillonné": "/kaʁijɔne/",
  "carillonnée": "/kaʁijɔne/",
  "carillonnées": "/kaʁijɔne/",
  "carillonnement": "/kaʁijɔnmɑ̃/",
  "carillonnements": "/kaʁijɔnmɑ̃/",
  "carillonnent": "/kaʁijɔn/",
  "carillonner": "/kaʁijɔne/",
  "carillonnera": "/kaʁijɔnəʁa/",
  "carillonnerai": "/kaʁijɔnəʁɛ/",
  "carillonneraient": "/kaʁijɔnəʁɛ/",
  "carillonnerais": "/kaʁijɔnəʁɛ/",
  "carillonnerait": "/kaʁijɔnəʁɛ/",
  "carillonneras": "/kaʁijɔnəʁa/",
  "carillonnèrent": "/kaʁijɔnɛʁ/",
  "carillonnerez": "/kaʁijɔnəʁe/",
  "carillonneriez": "/kaʁijɔnəʁje/",
  "carillonnerions": "/kaʁijɔnəʁjɔ̃/",
  "carillonnerons": "/kaʁijɔnəʁɔ̃/",
  "carillonneront": "/kaʁijɔnəʁɔ̃/",
  "carillonnes": "/kaʁijɔn/",
  "carillonnés": "/kaʁijɔne/",
  "carillonneur": "/kaʁijɔnœʁ/",
  "carillonneurs": "/kaʁijɔnœʁ/",
  "carillonneuse": "/kaʁijɔnøz/",
  "carillonnez": "/kaʁijɔne/",
  "carillonniez": "/kaʁijɔnje/",
  "carillonnions": "/kaʁijɔnjɔ̃/",
  "carillonnons": "/kaʁijɔnɔ̃/",
  "carillons": "/kaʁijɔ̃/",
  "carioca": "/kaʁiɔka/",
  "carions": "/kaʁjɔ̃/",
  "caris": "/kaʁi/",
  "cariste": "/kaʁist/",
  "caristes": "/kaʁist/",
  "caritatif": "/kaʁitatif/",
  "caritatifs": "/kaʁitatif/",
  "caritative": "/kaʁitativ/",
  "caritatives": "/kaʁitativ/",
  "carlingue": "/kaʁlɛ̃g/",
  "carlingues": "/kaʁlɛ̃g/",
  "carmagnole": "/kaʁmaɲɔl/",
  "carmagnoles": "/kaʁmaɲɔl/",
  "carme": "/kaʁm/",
  "carmel": "/kaʁmɛl/",
  "carmélite": "/kaʁmelit/",
  "carmélites": "/kaʁmelit/",
  "carmes": "/kaʁm/",
  "carmin": "/kaʁmɛ̃/",
  "carmine": "/kaʁmin/",
  "carmines": "/kaʁmin/",
  "carmins": "/kaʁmɛ̃/",
  "Carnac": "/kaʁnak/",
  "carnage": "/kaʁnaʒ/",
  "carnages": "/kaʁnaʒ/",
  "carnassier": "/kaʁnasje/",
  "carnassière": "/kaʁnasjɛʁ/",
  "carnassières": "/kaʁnasjɛʁ/",
  "carnassiers": "/kaʁnasje/",
  "carnation": "/kaʁnasjɔ̃/",
  "carnations": "/kaʁnasjɔ̃/",
  "carnaval": "/kaʁnaval/",
  "carnavalesque": "/kaʁnavalɛsk/",
  "carnavalesques": "/kaʁnavalɛsk/",
  "carnavals": "/kaʁnaval/",
  "carne": "/kaʁn/",
  "carné": "/kaʁne/",
  "carnée": "/kaʁne/",
  "carnées": "/kaʁne/",
  "carnes": "/kaʁn/",
  "carnés": "/kaʁne/",
  "carnet": "/kaʁnɛ/",
  "carnets": "/kaʁnɛ/",
  "carnivore": "/kaʁnivɔʁ/",
  "carnivores": "/kaʁnivɔʁ/",
  "carnotset": "/kaʁnotze/",
  "carnotsets": "/kaʁnotze/",
  "Caroline": "/kaʁɔlin/",
  "carolingien": "/kaʁɔlɛ̃ʒjɛ̃/",
  "carolingienne": "/kaʁɔlɛ̃ʒjɛn/",
  "carolingiennes": "/kaʁɔlɛ̃ʒjɛn/",
  "carolingiens": "/kaʁɔlɛ̃ʒjɛ̃/",
  "carotène": "/kaʁɔtɛn/",
  "carotènes": "/kaʁɔtɛn/",
  "carotide": "/kaʁɔtid/",
  "carotides": "/kaʁɔtid/",
  "carotta": "/kaʁɔta/",
  "carottai": "/kaʁɔtɛ/",
  "carottaient": "/kaʁɔtɛ/",
  "carottais": "/kaʁɔtɛ/",
  "carottait": "/kaʁɔtɛ/",
  "carottâmes": "/kaʁɔtam/",
  "carottant": "/kaʁɔtɑ̃/",
  "carottas": "/kaʁɔta/",
  "carottasse": "/kaʁɔtas/",
  "carottassent": "/kaʁɔtas/",
  "carottasses": "/kaʁɔtas/",
  "carottassiez": "/kaʁɔtasje/",
  "carottassions": "/kaʁɔtasjɔ̃/",
  "carottât": "/kaʁɔta/",
  "carottâtes": "/kaʁɔtat/",
  "carotte": "/kaʁɔt/",
  "carotté": "/kaʁɔte/",
  "carottée": "/kaʁɔte/",
  "carottées": "/kaʁɔte/",
  "carottent": "/kaʁɔt/",
  "carotter": "/kaʁɔte/",
  "carottera": "/kaʁɔtəʁa/",
  "carotterai": "/kaʁɔtəʁɛ/",
  "carotteraient": "/kaʁɔtəʁɛ/",
  "carotterais": "/kaʁɔtəʁɛ/",
  "carotterait": "/kaʁɔtəʁɛ/",
  "carotteras": "/kaʁɔtəʁa/",
  "carottèrent": "/kaʁɔtɛʁ/",
  "carotterez": "/kaʁɔtəʁe/",
  "carotteriez": "/kaʁɔtəʁje/",
  "carotterions": "/kaʁɔtəʁjɔ̃/",
  "carotterons": "/kaʁɔtəʁɔ̃/",
  "carotteront": "/kaʁɔtəʁɔ̃/",
  "carottes": "/kaʁɔt/",
  "carottés": "/kaʁɔte/",
  "carotteur": "/kaʁɔtœʁ/",
  "carotteurs": "/kaʁɔtœʁ/",
  "carotteuse": "/kaʁɔtøz/",
  "carotteuses": "/kaʁɔtøz/",
  "carottez": "/kaʁɔte/",
  "carottiez": "/kaʁɔtje/",
  "carottions": "/kaʁɔtjɔ̃/",
  "carottons": "/kaʁɔtɔ̃/",
  "caroube": "/kaʁub/",
  "caroubes": "/kaʁub/",
  "carpaccio": "/kaʁpatʃjo/",
  "Carpates": "/kaʁpat/",
  "carpe": "/kaʁp/",
  "carpes": "/kaʁp/",
  "carpette": "/kaʁpɛt/",
  "carpettes": "/kaʁpɛt/",
  "carquois": "/kaʁkwa/",
  "carra": "/kaʁa/",
  "carrai": "/kaʁɛ/",
  "carraient": "/kaʁɛ/",
  "carrais": "/kaʁɛ/",
  "carrait": "/kaʁɛ/",
  "carrâmes": "/kaʁam/",
  "carrant": "/kaʁɑ̃/",
  "carrare": "/kaʁaʁ/",
  "carrares": "/kaʁaʁ/",
  "carras": "/kaʁa/",
  "carrasse": "/kaʁas/",
  "carrassent": "/kaʁas/",
  "carrasses": "/kaʁas/",
  "carrassiez": "/kaʁasje/",
  "carrassions": "/kaʁasjɔ̃/",
  "carrât": "/kaʁa/",
  "carrâtes": "/kaʁat/",
  "carre": "/kaʁ/",
  "carré": "/kaʁe/",
  "Carré": "/kaʁe/",
  "carreau": "/kaʁo/",
  "carreaux": "/kaʁo/",
  "carrée": "/kaʁe/",
  "carrées": "/kaʁe/",
  "carrefour": "/kaʁfuʁ/",
  "carrefours": "/kaʁfuʁ/",
  "carrela": "/kaʁəla/",
  "carrelage": "/kaʁlaʒ/",
  "carrelages": "/kaʁlaʒ/",
  "carrelai": "/kaʁəlɛ/",
  "carrelaient": "/kaʁəlɛ/",
  "carrelais": "/kaʁəlɛ/",
  "carrelait": "/kaʁəlɛ/",
  "carrelâmes": "/kaʁɛlɑm/",
  "carrelant": "/kaʁlɑ̃/",
  "carrelas": "/kaʁəla/",
  "carrelasse": "/kaʁəlɑs/",
  "carrelassent": "/kaʁəlɑs/",
  "carrelasses": "/kaʁəlɑs/",
  "carrelassiez": "/kaʁəlɑsje/",
  "carrelassions": "/kaʁəlɑsjɔ̃/",
  "carrelât": "/kaʁəlɑ/",
  "carrelâtes": "/kaʁɛlɑt/",
  "carrelé": "/kaʁle/",
  "carrelée": "/kaʁle/",
  "carrelées": "/kaʁle/",
  "carreler": "/kaʁle/",
  "carrelèrent": "/kaʁəlɛʁ/",
  "carrelés": "/kaʁle/",
  "carrelet": "/kaʁlɛ/",
  "carrelets": "/kaʁlɛ/",
  "carreleur": "/kaʁlœʁ/",
  "carreleurs": "/kaʁlœʁ/",
  "carrelez": "/kaʁle/",
  "carreliez": "/kaʁəlje/",
  "carrelions": "/kaʁeljɔ̃/",
  "carrelle": "/kaʁɛl/",
  "carrellent": "/kaʁɛl/",
  "carrellera": "/kaʁələʁa/",
  "carrellerai": "/kaʁələʁe/",
  "carrelleraient": "/kaʁəlɛʁɛ/",
  "carrellerais": "/kaʁəlɛʁɛ/",
  "carrellerait": "/kaʁəlɛʁɛ/",
  "carrelleras": "/kaʁələʁa/",
  "carrellerez": "/kaʁələʁe/",
  "carrelleriez": "/kaʁəlɛʁje/",
  "carrellerions": "/kaʁəlɛʁjɔ̃/",
  "carrellerons": "/kaʁələʁɔ̃/",
  "carrelleront": "/kaʁələʁɔ̃/",
  "carrelles": "/kaʁɛl/",
  "carrelons": "/kaʁəlɔ̃/",
  "carrément": "/kaʁemɑ̃/",
  "carrent": "/kaʁ/",
  "carrer": "/kaʁe/",
  "carrera": "/kaʁəʁa/",
  "carrerai": "/kaʁəʁɛ/",
  "carreraient": "/kaʁəʁɛ/",
  "carrerais": "/kaʁəʁɛ/",
  "carrerait": "/kaʁəʁɛ/",
  "carreras": "/kaʁəʁa/",
  "carrèrent": "/kaʁɛʁ/",
  "carrerez": "/kaʁəʁe/",
  "carreriez": "/kaʁəʁje/",
  "carrerions": "/kaʁəʁjɔ̃/",
  "carrerons": "/kaʁəʁɔ̃/",
  "carreront": "/kaʁəʁɔ̃/",
  "carres": "/kaʁ/",
  "carrés": "/kaʁe/",
  "carrez": "/kaʁe/",
  "carrier": "/kaʁje/",
  "carrière": "/kaʁjɛʁ/",
  "carrières": "/kaʁjɛʁ/",
  "carriérisme": "/kaʁjeʁism/",
  "carriérismes": "/kaʁjeʁism/",
  "carriériste": "/kaʁjeʁist/",
  "carriéristes": "/kaʁjeʁist/",
  "carriers": "/kaʁje/",
  "carriez": "/kaʁje/",
  "carriole": "/kaʁjɔl/",
  "carrioles": "/kaʁjɔl/",
  "carrions": "/kaʁjɔ̃/",
  "carrons": "/kaʁɔ̃/",
  "carrossa": "/kaʁɔsa/",
  "carrossable": "/kaʁɔsabl/",
  "carrossables": "/kaʁɔsabl/",
  "carrossai": "/kaʁɔsɛ/",
  "carrossaient": "/kaʁɔsɛ/",
  "carrossais": "/kaʁɔsɛ/",
  "carrossait": "/kaʁɔsɛ/",
  "carrossâmes": "/kaʁɔsam/",
  "carrossant": "/kaʁɔsɑ̃/",
  "carrossas": "/kaʁɔsa/",
  "carrossasse": "/kaʁɔsas/",
  "carrossassent": "/kaʁɔsas/",
  "carrossasses": "/kaʁɔsas/",
  "carrossassiez": "/kaʁɔsasje/",
  "carrossassions": "/kaʁɔsasjɔ̃/",
  "carrossât": "/kaʁɔsa/",
  "carrossâtes": "/kaʁɔsat/",
  "carrosse": "/kaʁɔs/",
  "carrossé": "/kaʁɔse/",
  "carrossée": "/kaʁɔse/",
  "carrossées": "/kaʁɔse/",
  "carrossent": "/kaʁɔs/",
  "carrosser": "/kaʁɔse/",
  "carrossera": "/kaʁɔsəʁa/",
  "carrosserai": "/kaʁɔsəʁɛ/",
  "carrosseraient": "/kaʁɔsəʁɛ/",
  "carrosserais": "/kaʁɔsəʁɛ/",
  "carrosserait": "/kaʁɔsəʁɛ/",
  "carrosseras": "/kaʁɔsəʁa/",
  "carrossèrent": "/kaʁɔsɛʁ/",
  "carrosserez": "/kaʁɔsəʁe/",
  "carrosserie": "/kaʁɔsʁi/",
  "carrosseries": "/kaʁɔsʁi/",
  "carrosseriez": "/kaʁɔsəʁje/",
  "carrosserions": "/kaʁɔsəʁjɔ̃/",
  "carrosserons": "/kaʁɔsəʁɔ̃/",
  "carrosseront": "/kaʁɔsəʁɔ̃/",
  "carrosses": "/kaʁɔs/",
  "carrossés": "/kaʁɔse/",
  "carrossez": "/kaʁɔse/",
  "carrossier": "/kaʁɔsje/",
  "carrossiers": "/kaʁɔsje/",
  "carrossiez": "/kaʁɔsje/",
  "carrossions": "/kaʁɔsjɔ̃/",
  "carrossons": "/kaʁɔsɔ̃/",
  "carrousel": "/kaʁuzɛl/",
  "carrousels": "/kaʁuzɛl/",
  "carrure": "/kaʁyʁ/",
  "carrures": "/kaʁyʁ/",
  "carry": "/kaʁi/",
  "carrys": "/kaʁi/",
  "cars": "/kaʁ/",
  "carta": "/kaʁta/",
  "cartable": "/kaʁtabl/",
  "cartables": "/kaʁtabl/",
  "cartai": "/kaʁtɛ/",
  "cartaient": "/kaʁtɛ/",
  "cartais": "/kaʁtɛ/",
  "cartait": "/kaʁtɛ/",
  "cartâmes": "/kaʁtam/",
  "cartant": "/kaʁtɑ̃/",
  "cartas": "/kaʁta/",
  "cartasse": "/kaʁtas/",
  "cartassent": "/kaʁtas/",
  "cartasses": "/kaʁtas/",
  "cartassiez": "/kaʁtasje/",
  "cartassions": "/kaʁtasjɔ̃/",
  "cartât": "/kaʁta/",
  "cartâtes": "/kaʁtat/",
  "carte": "/kaʁt/",
  "carté": "/kaʁte/",
  "carte-lettre": "/kaʁtəlɛtʁ/",
  "carte-réponse": "/kaʁtʁepɔ̃s/",
  "cartée": "/kaʁte/",
  "cartées": "/kaʁte/",
  "cartel": "/kaʁtɛl/",
  "cartels": "/kaʁtɛl/",
  "cartent": "/kaʁt/",
  "carter": "/kaʁtɛʁ/, /kaʁte/",
  "cartera": "/kaʁtəʁa/",
  "carterai": "/kaʁtəʁɛ/",
  "carteraient": "/kaʁtəʁɛ/",
  "carterais": "/kaʁtəʁɛ/",
  "carterait": "/kaʁtəʁɛ/",
  "carteras": "/kaʁtəʁa/",
  "cartèrent": "/kaʁtɛʁ/",
  "carterez": "/kaʁtəʁe/",
  "carteriez": "/kaʁtəʁje/",
  "carterions": "/kaʁtəʁjɔ̃/",
  "carterons": "/kaʁtəʁɔ̃/",
  "carteront": "/kaʁtəʁɔ̃/",
  "carters": "/kaʁtɛʁ/",
  "cartes": "/kaʁt/",
  "cartés": "/kaʁte/",
  "cartésianisme": "/kaʁtezjanism/",
  "cartésianismes": "/kaʁtezjanism/",
  "cartésien": "/kaʁtezjɛ̃/",
  "cartésienne": "/kaʁtezjɛn/",
  "cartésiennes": "/kaʁtezjɛn/",
  "cartésiens": "/kaʁtezjɛ̃/",
  "cartez": "/kaʁte/",
  "Carthage": "/kaʁtaʒ/",
  "carthaginois": "/kaʁtaʒinwa/",
  "carthaginoise": "/kaʁtaʒinwaz/",
  "carthaginoises": "/kaʁtaʒinwaz/",
  "cartiez": "/kaʁtje/",
  "cartilage": "/kaʁtilaʒ/",
  "cartilages": "/kaʁtilaʒ/",
  "cartilagineuse": "/kaʁtilaʒinøz/",
  "cartilagineuses": "/kaʁtilaʒinøz/",
  "cartilagineux": "/kaʁtilaʒinø/",
  "cartions": "/kaʁtjɔ̃/",
  "cartographe": "/kaʁtɔgʁaf/",
  "cartographes": "/kaʁtɔgʁaf/",
  "cartographie": "/kaʁtɔgʁafi/",
  "cartographies": "/kaʁtɔgʁafi/",
  "cartomancie": "/kaʁtɔmɑ̃si/",
  "cartomancien": "/kaʁtɔmɑ̃sjɛ̃/",
  "cartomancienne": "/kaʁtɔmɑ̃sjɛn/",
  "cartomanciennes": "/kaʁtɔmɑ̃sjɛn/",
  "cartomanciens": "/kaʁtɔmɑ̃sjɛ̃/",
  "cartomancies": "/kaʁtɔmɑ̃si/",
  "carton": "/kaʁtɔ̃/",
  "carton-pâte": "/kaʁtɔ̃pat/",
  "carton-pâtes": "/kaʁtɔ̃pat/",
  "cartonna": "/kaʁtɔna/",
  "cartonnage": "/kaʁtɔnaʒ/",
  "cartonnages": "/kaʁtɔnaʒ/",
  "cartonnai": "/kaʁtɔnɛ/",
  "cartonnaient": "/kaʁtɔnɛ/",
  "cartonnais": "/kaʁtɔnɛ/",
  "cartonnait": "/kaʁtɔnɛ/",
  "cartonnâmes": "/kaʁtɔnam/",
  "cartonnant": "/kaʁtɔnɑ̃/",
  "cartonnas": "/kaʁtɔna/",
  "cartonnasse": "/kaʁtɔnas/",
  "cartonnassent": "/kaʁtɔnas/",
  "cartonnasses": "/kaʁtɔnas/",
  "cartonnassiez": "/kaʁtɔnasje/",
  "cartonnassions": "/kaʁtɔnasjɔ̃/",
  "cartonnât": "/kaʁtɔna/",
  "cartonnâtes": "/kaʁtɔnat/",
  "cartonne": "/kaʁtɔn/",
  "cartonné": "/kaʁtɔne/",
  "cartonnée": "/kaʁtɔne/",
  "cartonnées": "/kaʁtɔne/",
  "cartonnent": "/kaʁtɔn/",
  "cartonner": "/kaʁtɔne/",
  "cartonnera": "/kaʁtɔnəʁa/",
  "cartonnerai": "/kaʁtɔnəʁɛ/",
  "cartonneraient": "/kaʁtɔnəʁɛ/",
  "cartonnerais": "/kaʁtɔnəʁɛ/",
  "cartonnerait": "/kaʁtɔnəʁɛ/",
  "cartonneras": "/kaʁtɔnəʁa/",
  "cartonnèrent": "/kaʁtɔnɛʁ/",
  "cartonnerez": "/kaʁtɔnəʁe/",
  "cartonneriez": "/kaʁtɔnəʁje/",
  "cartonnerions": "/kaʁtɔnəʁjɔ̃/",
  "cartonnerons": "/kaʁtɔnəʁɔ̃/",
  "cartonneront": "/kaʁtɔnəʁɔ̃/",
  "cartonnes": "/kaʁtɔn/",
  "cartonnés": "/kaʁtɔne/",
  "cartonneuse": "/kaʁtɔnøz/",
  "cartonneuses": "/kaʁtɔnøz/",
  "cartonneux": "/kaʁtɔnø/",
  "cartonnez": "/kaʁtɔne/",
  "cartonniez": "/kaʁtɔnje/",
  "cartonnions": "/kaʁtɔnjɔ̃/",
  "cartonnons": "/kaʁtɔnɔ̃/",
  "cartons": "/kaʁtɔ̃/",
  "cartophilie": "/kaʁtɔfili/",
  "cartothèque": "/kaʁtɔtɛk/",
  "cartothèques": "/kaʁtɔtɛk/",
  "cartouche": "/kaʁtuʃ/",
  "cartoucherie": "/kaʁtuʃʁi/",
  "cartoucheries": "/kaʁtuʃʁi/",
  "cartouches": "/kaʁtuʃ/",
  "cartouchière": "/kaʁtuʃjɛʁ/",
  "cartouchières": "/kaʁtuʃjɛʁ/",
  "cary": "/kaʁi/",
  "caryatide": "/kaʁjatid/"
}