{
  "feu": "/fø/",
  "feu follet": "/føfɔlɛ/",
  "feuilla": "/fœja/",
  "feuillage": "/fœjaʒ/",
  "feuillages": "/fœjaʒ/",
  "feuillai": "/fœjɛ/",
  "feuillaient": "/fœjɛ/",
  "feuillais": "/fœjɛ/",
  "feuillaison": "/fœjɛzɔ̃/",
  "feuillaisons": "/fœjɛzɔ̃/",
  "feuillait": "/fœjɛ/",
  "feuillâmes": "/fœjam/",
  "feuillant": "/fœjɑ̃/",
  "feuillantine": "/fœjɑ̃tin/",
  "feuillantines": "/fœjɑ̃tin/",
  "feuillas": "/fœja/",
  "feuillasse": "/fœjas/",
  "feuillassent": "/fœjas/",
  "feuillasses": "/fœjas/",
  "feuillassiez": "/fœjasje/",
  "feuillassions": "/fœjasjɔ̃/",
  "feuillât": "/fœja/",
  "feuillâtes": "/fœjat/",
  "feuille": "/fœj/",
  "feuillé": "/fœje/",
  "feuille-à-feuille": "/fœjafœj/",
  "feuille-morte": "/fœjmɔʁt/",
  "feuillée": "/fœje/",
  "feuillées": "/fœje/",
  "feuillent": "/fœj/",
  "feuiller": "/fœje/",
  "feuillera": "/fœjəʁa/",
  "feuillerai": "/fœjəʁɛ/",
  "feuilleraient": "/fœjəʁɛ/",
  "feuillerais": "/fœjəʁɛ/",
  "feuillerait": "/fœjəʁɛ/",
  "feuilleras": "/fœjəʁa/",
  "feuillèrent": "/fœjɛʁ/",
  "feuillerez": "/fœjəʁe/",
  "feuilleriez": "/fœjəʁje/",
  "feuillerions": "/fœjəʁjɔ̃/",
  "feuillerons": "/fœjəʁɔ̃/",
  "feuilleront": "/fœjəʁɔ̃/",
  "feuilles": "/fœj/",
  "feuillés": "/fœje/",
  "feuillet": "/fœjɛ/",
  "feuilleta": "/fœjəta/",
  "feuilletai": "/fœjətɛ/",
  "feuilletaient": "/fœjətɛ/",
  "feuilletais": "/fœjətɛ/",
  "feuilletait": "/fœjətɛ/",
  "feuilletâmes": "/fœjətɑm/",
  "feuilletant": "/fœjətɑ̃/",
  "feuilletas": "/fœjəta/",
  "feuilletasse": "/fœjətas/",
  "feuilletassent": "/fœjətas/",
  "feuilletasses": "/fœjətas/",
  "feuilletassiez": "/fœjətasje/",
  "feuilletassions": "/fœjətasjɔ̃/",
  "feuilletât": "/fœjətɑ/",
  "feuilletâtes": "/fœjətɑt/",
  "feuilleté": "/fœjte/",
  "feuilletée": "/fœjəte/",
  "feuilletées": "/fœjəte/",
  "feuilleter": "/fœjte/",
  "feuilletèrent": "/fœjətɛʁ/",
  "feuilletés": "/fœjəte/",
  "feuilletez": "/fœjəte/",
  "feuilletiez": "/fœjətje/",
  "feuilletions": "/fœjətjɔ̃/",
  "feuilleton": "/fœjtɔ̃/",
  "feuilletoniste": "/fœjtɔnist/",
  "feuilletonistes": "/fœjtɔnist/",
  "feuilletons": "/fœjətɔ̃/",
  "feuillets": "/fœjɛ/",
  "feuillette": "/fœjɛt/",
  "feuillettent": "/fœjɛt/",
  "feuillettera": "/fœjɛtəʁa/",
  "feuilletterai": "/fœjɛtəʁɛ/",
  "feuilletteraient": "/fœjɛtəʁɛ/",
  "feuilletterais": "/fœjɛtəʁɛ/",
  "feuilletterait": "/fœjɛtəʁɛ/",
  "feuilletteras": "/fœjɛtəʁa/",
  "feuilletterez": "/fœjɛtəʁe/",
  "feuilletteriez": "/fœjɛtəʁje/",
  "feuilletterions": "/fœjɛtəʁjɔ̃/",
  "feuilletterons": "/fœjɛtəʁɔ̃/",
  "feuilletteront": "/fœjɛtəʁɔ̃/",
  "feuillettes": "/fœjɛt/",
  "feuillez": "/fœje/",
  "feuilliez": "/fœje/",
  "feuillions": "/fœjɔ̃/",
  "feuillons": "/fœjɔ̃/",
  "feuillu": "/fœjy/",
  "feuillure": "/fœjyʁ/",
  "feuillures": "/fœjyʁ/",
  "feuillus": "/fœjy/",
  "feula": "/føla/",
  "feulai": "/følɛ/",
  "feulaient": "/følɛ/",
  "feulais": "/følɛ/",
  "feulait": "/følɛ/",
  "feulâmes": "/følam/",
  "feulant": "/følɑ̃/",
  "feulas": "/føla/",
  "feulasse": "/følas/",
  "feulassent": "/følas/",
  "feulasses": "/følas/",
  "feulassiez": "/følasje/",
  "feulassions": "/følasjɔ̃/",
  "feulât": "/føla/",
  "feulâtes": "/følat/",
  "feule": "/føl/",
  "feulé": "/føle/",
  "feulée": "/føle/",
  "feulées": "/føle/",
  "feulement": "/følmɑ̃/",
  "feulements": "/følmɑ̃/",
  "feulent": "/føl/",
  "feuler": "/føle/",
  "feulera": "/føləʁa/",
  "feulerai": "/føləʁɛ/",
  "feuleraient": "/føləʁɛ/",
  "feulerais": "/føləʁɛ/",
  "feulerait": "/føləʁɛ/",
  "feuleras": "/føləʁa/",
  "feulèrent": "/følɛʁ/",
  "feulerez": "/føləʁe/",
  "feuleriez": "/føləʁje/",
  "feulerions": "/føləʁjɔ̃/",
  "feulerons": "/føləʁɔ̃/",
  "feuleront": "/føləʁɔ̃/",
  "feules": "/føl/",
  "feulés": "/føle/",
  "feulez": "/føle/",
  "feuliez": "/følje/",
  "feulions": "/føljɔ̃/",
  "feulons": "/følɔ̃/",
  "feus": "/fø/",
  "feutra": "/føtʁa/",
  "feutrage": "/føtʁaʒ/",
  "feutrages": "/føtʁaʒ/",
  "feutrai": "/føtʁɛ/",
  "feutraient": "/føtʁɛ/",
  "feutrais": "/føtʁɛ/",
  "feutrait": "/føtʁɛ/",
  "feutrâmes": "/føtʁam/",
  "feutrant": "/føtʁɑ̃/",
  "feutras": "/føtʁa/",
  "feutrasse": "/føtʁas/",
  "feutrassent": "/føtʁas/",
  "feutrasses": "/føtʁas/",
  "feutrassiez": "/føtʁasje/",
  "feutrassions": "/føtʁasjɔ̃/",
  "feutrât": "/føtʁa/",
  "feutrâtes": "/føtʁat/",
  "feutre": "/føtʁ/",
  "feutré": "/føtʁe/",
  "feutrée": "/føtʁe/",
  "feutrées": "/føtʁe/",
  "feutrent": "/føtʁ/",
  "feutrer": "/føtʁe/",
  "feutrera": "/føtʁəʁa/",
  "feutrerai": "/føtʁəʁɛ/",
  "feutreraient": "/føtʁəʁɛ/",
  "feutrerais": "/føtʁəʁɛ/",
  "feutrerait": "/føtʁəʁɛ/",
  "feutreras": "/føtʁəʁa/",
  "feutrèrent": "/føtʁɛʁ/",
  "feutrerez": "/føtʁəʁe/",
  "feutreriez": "/føtʁəʁje/",
  "feutrerions": "/føtʁəʁjɔ̃/",
  "feutrerons": "/føtʁəʁɔ̃/",
  "feutreront": "/føtʁəʁɔ̃/",
  "feutres": "/føtʁ/",
  "feutrés": "/føtʁe/",
  "feutrez": "/føtʁe/",
  "feutriez": "/føtʁje/",
  "feutrine": "/føtʁin/",
  "feutrines": "/føtʁin/",
  "feutrions": "/føtʁjɔ̃/",
  "feutrons": "/føtʁɔ̃/"
}