{
  "imbattable": "/ɛ̃batabl/",
  "imbattables": "/ɛ̃batabl/",
  "imbécile": "/ɛ̃besil/",
  "imbéciles": "/ɛ̃besil/",
  "imbécillité": "/ɛ̃besilite/",
  "imbécillités": "/ɛ̃besilite/",
  "imberbe": "/ɛ̃bɛʁb/",
  "imberbes": "/ɛ̃bɛʁb/",
  "imbiba": "/ɛ̃biba/",
  "imbibai": "/ɛ̃bibɛ/",
  "imbibaient": "/ɛ̃bibɛ/",
  "imbibais": "/ɛ̃bibɛ/",
  "imbibait": "/ɛ̃bibɛ/",
  "imbibâmes": "/ɛ̃bibam/",
  "imbibant": "/ɛ̃bibɑ̃/",
  "imbibas": "/ɛ̃biba/",
  "imbibasse": "/ɛ̃bibas/",
  "imbibassent": "/ɛ̃bibas/",
  "imbibasses": "/ɛ̃bibas/",
  "imbibassiez": "/ɛ̃bibasje/",
  "imbibassions": "/ɛ̃bibasjɔ̃/",
  "imbibât": "/ɛ̃biba/",
  "imbibâtes": "/ɛ̃bibat/",
  "imbibe": "/ɛ̃bib/",
  "imbibé": "/ɛ̃bibe/",
  "imbibée": "/ɛ̃bibe/",
  "imbibées": "/ɛ̃bibe/",
  "imbibent": "/ɛ̃bib/",
  "imbiber": "/ɛ̃bibe/",
  "imbibera": "/ɛ̃bibəʁa/",
  "imbiberai": "/ɛ̃bibəʁɛ/",
  "imbiberaient": "/ɛ̃bibəʁɛ/",
  "imbiberais": "/ɛ̃bibəʁɛ/",
  "imbiberait": "/ɛ̃bibəʁɛ/",
  "imbiberas": "/ɛ̃bibəʁa/",
  "imbibèrent": "/ɛ̃bibɛʁ/",
  "imbiberez": "/ɛ̃bibəʁe/",
  "imbiberiez": "/ɛ̃bibəʁje/",
  "imbiberions": "/ɛ̃bibəʁjɔ̃/",
  "imbiberons": "/ɛ̃bibəʁɔ̃/",
  "imbiberont": "/ɛ̃bibəʁɔ̃/",
  "imbibes": "/ɛ̃bib/",
  "imbibés": "/ɛ̃bibe/",
  "imbibez": "/ɛ̃bibe/",
  "imbibiez": "/ɛ̃bibje/",
  "imbibions": "/ɛ̃bibjɔ̃/",
  "imbibons": "/ɛ̃bibɔ̃/",
  "imbrication": "/ɛ̃bʁikasjɔ̃/",
  "imbrications": "/ɛ̃bʁikasjɔ̃/",
  "imbriqua": "/ɛ̃bʁika/",
  "imbriquai": "/ɛ̃bʁikɛ/",
  "imbriquaient": "/ɛ̃bʁikɛ/",
  "imbriquais": "/ɛ̃bʁikɛ/",
  "imbriquait": "/ɛ̃bʁikɛ/",
  "imbriquâmes": "/ɛ̃bʁikam/",
  "imbriquant": "/ɛ̃bʁikɑ̃/",
  "imbriquas": "/ɛ̃bʁika/",
  "imbriquasse": "/ɛ̃bʁikas/",
  "imbriquassent": "/ɛ̃bʁikas/",
  "imbriquasses": "/ɛ̃bʁikas/",
  "imbriquassiez": "/ɛ̃bʁikasje/",
  "imbriquassions": "/ɛ̃bʁikasjɔ̃/",
  "imbriquât": "/ɛ̃bʁika/",
  "imbriquâtes": "/ɛ̃bʁikat/",
  "imbrique": "/ɛ̃bʁik/",
  "imbriqué": "/ɛ̃bʁike/",
  "imbriquée": "/ɛ̃bʁike/",
  "imbriquées": "/ɛ̃bʁike/",
  "imbriquent": "/ɛ̃bʁik/",
  "imbriquer": "/ɛ̃bʁike/",
  "imbriquera": "/ɛ̃bʁikəʁa/",
  "imbriquerai": "/ɛ̃bʁikəʁɛ/",
  "imbriqueraient": "/ɛ̃bʁikəʁɛ/",
  "imbriquerais": "/ɛ̃bʁikəʁɛ/",
  "imbriquerait": "/ɛ̃bʁikəʁɛ/",
  "imbriqueras": "/ɛ̃bʁikəʁa/",
  "imbriquèrent": "/ɛ̃bʁikɛʁ/",
  "imbriquerez": "/ɛ̃bʁikəʁe/",
  "imbriqueriez": "/ɛ̃bʁikəʁje/",
  "imbriquerions": "/ɛ̃bʁikəʁjɔ̃/",
  "imbriquerons": "/ɛ̃bʁikəʁɔ̃/",
  "imbriqueront": "/ɛ̃bʁikəʁɔ̃/",
  "imbriques": "/ɛ̃bʁik/",
  "imbriqués": "/ɛ̃bʁike/",
  "imbriquez": "/ɛ̃bʁike/",
  "imbriquiez": "/ɛ̃bʁikje/",
  "imbriquions": "/ɛ̃bʁikjɔ̃/",
  "imbriquons": "/ɛ̃bʁikɔ̃/",
  "imbroglio": "/ɛ̃bʁɔljo/, /ɛ̃bʁɔgljo/",
  "imbroglios": "/ɛ̃bʁɔljo/, /ɛ̃bʁɔgljo/",
  "imbu": "/ɛ̃by/",
  "imbus": "/ɛ̃by/",
  "imbuvable": "/ɛ̃byvabl/",
  "imbuvables": "/ɛ̃byvabl/"
}