{
  "oscar": "/ɔskaʁ/",
  "oscariser": "/ɔskaʁize/",
  "oscars": "/ɔskaʁ/",
  "oscilla": "/ɔsila/",
  "oscillai": "/ɔsilɛ/",
  "oscillaient": "/ɔsilɛ/",
  "oscillais": "/ɔsilɛ/",
  "oscillait": "/ɔsilɛ/",
  "oscillâmes": "/ɔsilam/",
  "oscillant": "/ɔsilɑ̃/",
  "oscillante": "/ɔsilɑ̃t/",
  "oscillantes": "/ɔsilɑ̃t/",
  "oscillants": "/ɔsilɑ̃/",
  "oscillas": "/ɔsila/",
  "oscillasse": "/ɔsilas/",
  "oscillassent": "/ɔsilas/",
  "oscillasses": "/ɔsilas/",
  "oscillassiez": "/ɔsilasje/",
  "oscillassions": "/ɔsilasjɔ̃/",
  "oscillât": "/ɔsila/",
  "oscillâtes": "/ɔsilat/",
  "oscillateur": "/ɔsilatœʁ/",
  "oscillateurs": "/ɔsilatœʁ/",
  "oscillation": "/ɔsilasjɔ̃/",
  "oscillations": "/ɔsilasjɔ̃/",
  "oscillatoire": "/ɔsilatwaʁ/",
  "oscillatoires": "/ɔsilatwaʁ/",
  "oscille": "/ɔsil/",
  "oscillé": "/ɔsile/",
  "oscillée": "/ɔsile/",
  "oscillées": "/ɔsile/",
  "oscillent": "/ɔsil/",
  "osciller": "/ɔsile/",
  "oscillera": "/ɔsiləʁa/",
  "oscillerai": "/ɔsiləʁɛ/",
  "oscilleraient": "/ɔsiləʁɛ/",
  "oscillerais": "/ɔsiləʁɛ/",
  "oscillerait": "/ɔsiləʁɛ/",
  "oscilleras": "/ɔsiləʁa/",
  "oscillèrent": "/ɔsilɛʁ/",
  "oscillerez": "/ɔsiləʁe/",
  "oscilleriez": "/ɔsiləʁje/",
  "oscillerions": "/ɔsiləʁjɔ̃/",
  "oscillerons": "/ɔsiləʁɔ̃/",
  "oscilleront": "/ɔsiləʁɔ̃/",
  "oscilles": "/ɔsil/",
  "oscillés": "/ɔsile/",
  "oscillez": "/ɔsile/",
  "oscilliez": "/ɔsilje/",
  "oscillions": "/ɔsiljɔ̃/",
  "oscillogramme": "/ɔsilɔgʁam/",
  "oscillogrammes": "/ɔsilɔgʁam/",
  "oscillographe": "/ɔsilɔgʁaf/",
  "oscillographes": "/ɔsilɔgʁaf/",
  "oscillons": "/ɔsilɔ̃/",
  "oscilloscope": "/ɔsilɔskɔp/"
}