{
  "radar": "/ʁadaʁ/",
  "radars": "/ʁadaʁ/",
  "rade": "/ʁad/",
  "radeau": "/ʁado/",
  "radeaux": "/ʁado/",
  "rades": "/ʁad/",
  "radia": "/ʁadja/",
  "radiai": "/ʁadjɛ/",
  "radiaient": "/ʁadjɛ/",
  "radiais": "/ʁadjɛ/",
  "radiait": "/ʁadjɛ/",
  "radial": "/ʁadjal/",
  "radiale": "/ʁadjal/",
  "radiales": "/ʁadjal/",
  "radiâmes": "/ʁadjam/",
  "radian": "/ʁadjɑ̃/",
  "radians": "/ʁadjɑ̃/",
  "radiant": "/ʁadjɑ̃/",
  "radiante": "/ʁadjɑ̃t/",
  "radias": "/ʁadja/",
  "radiasse": "/ʁadjas/",
  "radiassent": "/ʁadjas/",
  "radiasses": "/ʁadjas/",
  "radiassiez": "/ʁadjasje/",
  "radiassions": "/ʁadjasjɔ̃/",
  "radiât": "/ʁadja/",
  "radiâtes": "/ʁadjat/",
  "radiateur": "/ʁadjatœʁ/",
  "radiateurs": "/ʁadjatœʁ/",
  "radiatif": "/ʁadjatif/",
  "radiatifs": "/ʁadjatif/",
  "radiation": "/ʁadjasjɔ̃/",
  "radiations": "/ʁadjasjɔ̃/",
  "radiative": "/ʁadjativ/",
  "radiatives": "/ʁadjativ/",
  "radiaux": "/ʁadjo/",
  "radical": "/ʁadikal/",
  "radical-socialisme": "/ʁadikalsɔsjalism/",
  "radical-socialiste": "/ʁadikalsɔsjalist/",
  "radicale": "/ʁadikal/",
  "radicalement": "/ʁadikalmɑ̃/",
  "radicales": "/ʁadikal/",
  "radicalisa": "/ʁadikaliza/",
  "radicalisai": "/ʁadikalizɛ/",
  "radicalisaient": "/ʁadikalizɛ/",
  "radicalisais": "/ʁadikalizɛ/",
  "radicalisait": "/ʁadikalizɛ/",
  "radicalisâmes": "/ʁadikalizam/",
  "radicalisant": "/ʁadikalizɑ̃/",
  "radicalisas": "/ʁadikaliza/",
  "radicalisasse": "/ʁadikalizas/",
  "radicalisassent": "/ʁadikalizas/",
  "radicalisasses": "/ʁadikalizas/",
  "radicalisassiez": "/ʁadikalizasje/",
  "radicalisassions": "/ʁadikalizasjɔ̃/",
  "radicalisât": "/ʁadikaliza/",
  "radicalisâtes": "/ʁadikalizat/",
  "radicalisation": "/ʁadikalizasjɔ̃/",
  "radicalisations": "/ʁadikalizasjɔ̃/",
  "radicalise": "/ʁadikaliz/",
  "radicalisé": "/ʁadikalize/",
  "radicalisée": "/ʁadikalize/",
  "radicalisées": "/ʁadikalize/",
  "radicalisent": "/ʁadikaliz/",
  "radicaliser": "/ʁadikalize/",
  "radicalisera": "/ʁadikalizəʁa/",
  "radicaliserai": "/ʁadikalizəʁɛ/",
  "radicaliseraient": "/ʁadikalizəʁɛ/",
  "radicaliserais": "/ʁadikalizəʁɛ/",
  "radicaliserait": "/ʁadikalizəʁɛ/",
  "radicaliseras": "/ʁadikalizəʁa/",
  "radicalisèrent": "/ʁadikalizɛʁ/",
  "radicaliserez": "/ʁadikalizəʁe/",
  "radicaliseriez": "/ʁadikalizəʁje/",
  "radicaliserions": "/ʁadikalizəʁjɔ̃/",
  "radicaliserons": "/ʁadikalizəʁɔ̃/",
  "radicaliseront": "/ʁadikalizəʁɔ̃/",
  "radicalises": "/ʁadikaliz/",
  "radicalisés": "/ʁadikalize/",
  "radicalisez": "/ʁadikalize/",
  "radicalisiez": "/ʁadikalizje/",
  "radicalisions": "/ʁadikalizjɔ̃/",
  "radicalisme": "/ʁadikalism/",
  "radicalismes": "/ʁadikalism/",
  "radicalisons": "/ʁadikalizɔ̃/",
  "radicaux": "/ʁadiko/",
  "radicelle": "/ʁadisɛl/",
  "radicelles": "/ʁadisɛl/",
  "radicule": "/ʁadikyl/",
  "radie": "/ʁadi/",
  "radié": "/ʁadje/",
  "radiée": "/ʁadje/",
  "radiées": "/ʁadje/",
  "radient": "/ʁadi/",
  "radier": "/ʁadje/",
  "radiera": "/ʁadjəʁa/",
  "radierai": "/ʁadjəʁɛ/",
  "radieraient": "/ʁadjəʁɛ/",
  "radierais": "/ʁadjəʁɛ/",
  "radierait": "/ʁadjəʁɛ/",
  "radieras": "/ʁadjəʁa/",
  "radièrent": "/ʁadjɛʁ/",
  "radierez": "/ʁadjəʁe/",
  "radieriez": "/ʁadjəʁje/",
  "radierions": "/ʁadjəʁjɔ̃/",
  "radierons": "/ʁadjəʁɔ̃/",
  "radieront": "/ʁadjəʁɔ̃/",
  "radies": "/ʁadi/",
  "radiés": "/ʁadje/",
  "radiesthésie": "/ʁadjɛstezi/",
  "radiesthésies": "/ʁadjɛstezi/",
  "radiesthésiste": "/ʁadjɛstezist/",
  "radiesthésistes": "/ʁadjɛstezist/",
  "radieuse": "/ʁadjøz/",
  "radieuses": "/ʁadjøz/",
  "radieux": "/ʁadjø/",
  "radiez": "/ʁadje/",
  "radiiez": "/ʁadije/",
  "radiions": "/ʁadijɔ̃/",
  "radin": "/ʁadɛ̃/",
  "radina": "/ʁadina/",
  "radinai": "/ʁadinɛ/",
  "radinaient": "/ʁadinɛ/",
  "radinais": "/ʁadinɛ/",
  "radinait": "/ʁadinɛ/",
  "radinâmes": "/ʁadinam/",
  "radinant": "/ʁadinɑ̃/",
  "radinas": "/ʁadina/",
  "radinasse": "/ʁadinas/",
  "radinassent": "/ʁadinas/",
  "radinasses": "/ʁadinas/",
  "radinassiez": "/ʁadinasje/",
  "radinassions": "/ʁadinasjɔ̃/",
  "radinât": "/ʁadina/",
  "radinâtes": "/ʁadinat/",
  "radine": "/ʁadin/",
  "radiné": "/ʁadine/",
  "radinée": "/ʁadine/",
  "radinées": "/ʁadine/",
  "radinent": "/ʁadin/",
  "radiner": "/ʁadine/",
  "radinera": "/ʁadinəʁa/",
  "radinerai": "/ʁadinəʁɛ/",
  "radineraient": "/ʁadinəʁɛ/",
  "radinerais": "/ʁadinəʁɛ/",
  "radinerait": "/ʁadinəʁɛ/",
  "radineras": "/ʁadinəʁa/",
  "radinèrent": "/ʁadinɛʁ/",
  "radinerez": "/ʁadinəʁe/",
  "radinerie": "/ʁadinʁi/",
  "radineries": "/ʁadinʁi/",
  "radineriez": "/ʁadinəʁje/",
  "radinerions": "/ʁadinəʁjɔ̃/",
  "radinerons": "/ʁadinəʁɔ̃/",
  "radineront": "/ʁadinəʁɔ̃/",
  "radines": "/ʁadin/",
  "radinés": "/ʁadine/",
  "radinez": "/ʁadine/",
  "radiniez": "/ʁadinje/",
  "radinions": "/ʁadinjɔ̃/",
  "radinons": "/ʁadinɔ̃/",
  "radins": "/ʁadɛ̃/",
  "radio": "/ʁadjo/",
  "radio-taxi": "/ʁadjɔtaksi/",
  "radio-taxis": "/ʁadjɔtaksi/",
  "radioactif": "/ʁadjɔaktif/",
  "radioactifs": "/ʁadjɔaktif/",
  "radioactive": "/ʁadjɔaktiv/",
  "radioactives": "/ʁadjɔaktiv/",
  "radioactivité": "/ʁadjɔaktivite/",
  "radioactivités": "/ʁadjɔaktivite/",
  "radioamateur": "/ʁadjɔamatœʁ/",
  "radioamateurs": "/ʁadjɔamatœʁ/",
  "radioamatrice": "/ʁadjɔamatʁis/",
  "radioamatrices": "/ʁadjɔamatʁis/",
  "radiobalisa": "/ʁadjɔbaliza/",
  "radiobalisai": "/ʁadjɔbalizɛ/",
  "radiobalisaient": "/ʁadjɔbalizɛ/",
  "radiobalisais": "/ʁadjɔbalizɛ/",
  "radiobalisait": "/ʁadjɔbalizɛ/",
  "radiobalisâmes": "/ʁadjɔbalizam/",
  "radiobalisant": "/ʁadjɔbalizɑ̃/",
  "radiobalisas": "/ʁadjɔbaliza/",
  "radiobalisasse": "/ʁadjɔbalizas/",
  "radiobalisassent": "/ʁadjɔbalizas/",
  "radiobalisasses": "/ʁadjɔbalizas/",
  "radiobalisassiez": "/ʁadjɔbalizasje/",
  "radiobalisassions": "/ʁadjɔbalizasjɔ̃/",
  "radiobalisât": "/ʁadjɔbaliza/",
  "radiobalisâtes": "/ʁadjɔbalizat/",
  "radiobalise": "/ʁadjɔbaliz/",
  "radiobalisé": "/ʁadjɔbalize/",
  "radiobalisée": "/ʁadjɔbalize/",
  "radiobalisées": "/ʁadjɔbalize/",
  "radiobalisent": "/ʁadjɔbaliz/",
  "radiobaliser": "/ʁadjɔbalize/",
  "radiobalisera": "/ʁadjɔbalizəʁa/",
  "radiobaliserai": "/ʁadjɔbalizəʁɛ/",
  "radiobaliseraient": "/ʁadjɔbalizəʁɛ/",
  "radiobaliserais": "/ʁadjɔbalizəʁɛ/",
  "radiobaliserait": "/ʁadjɔbalizəʁɛ/",
  "radiobaliseras": "/ʁadjɔbalizəʁa/",
  "radiobalisèrent": "/ʁadjɔbalizɛʁ/",
  "radiobaliserez": "/ʁadjɔbalizəʁe/",
  "radiobaliseriez": "/ʁadjɔbalizəʁje/",
  "radiobaliserions": "/ʁadjɔbalizəʁjɔ̃/",
  "radiobaliserons": "/ʁadjɔbalizəʁɔ̃/",
  "radiobaliseront": "/ʁadjɔbalizəʁɔ̃/",
  "radiobalises": "/ʁadjɔbaliz/",
  "radiobalisés": "/ʁadjɔbalize/",
  "radiobalisez": "/ʁadjɔbalize/",
  "radiobalisiez": "/ʁadjɔbalizje/",
  "radiobalisions": "/ʁadjɔbalizjɔ̃/",
  "radiobalisons": "/ʁadjɔbalizɔ̃/",
  "radiocarbone": "/ʁadjɔkaʁbɔn/",
  "radiocarbones": "/ʁadjɔkaʁbɔn/",
  "radiocassette": "/ʁadjɔkasɛt/",
  "radiocassettes": "/ʁadjɔkasɛt/",
  "radiocommande": "/ʁadjɔkɔmɑ̃d/",
  "radiocommunication": "/ʁadjɔkɔmynikasjɔ̃/",
  "radiocommunications": "/ʁadjɔkɔmynikasjɔ̃/",
  "radiodétection": "/ʁadjɔdetɛksjɔ̃/",
  "radiodiffusa": "/ʁadjɔdifyza/",
  "radiodiffusai": "/ʁadjɔdifyzɛ/",
  "radiodiffusaient": "/ʁadjɔdifyzɛ/",
  "radiodiffusais": "/ʁadjɔdifyzɛ/",
  "radiodiffusait": "/ʁadjɔdifyzɛ/",
  "radiodiffusâmes": "/ʁadjɔdifyzam/",
  "radiodiffusant": "/ʁadjɔdifyzɑ̃/",
  "radiodiffusas": "/ʁadjɔdifyza/",
  "radiodiffusasse": "/ʁadjɔdifyzas/",
  "radiodiffusassent": "/ʁadjɔdifyzas/",
  "radiodiffusasses": "/ʁadjɔdifyzas/",
  "radiodiffusassiez": "/ʁadjɔdifyzasje/",
  "radiodiffusassions": "/ʁadjɔdifyzasjɔ̃/",
  "radiodiffusât": "/ʁadjɔdifyza/",
  "radiodiffusâtes": "/ʁadjɔdifyzat/",
  "radiodiffuse": "/ʁadjɔdifyz/",
  "radiodiffusé": "/ʁadjɔdifyze/",
  "radiodiffusée": "/ʁadjɔdifyze/",
  "radiodiffusées": "/ʁadjɔdifyze/",
  "radiodiffusent": "/ʁadjɔdifyz/",
  "radiodiffuser": "/ʁadjɔdifyze/",
  "radiodiffusera": "/ʁadjɔdifyzəʁa/",
  "radiodiffuserai": "/ʁadjɔdifyzəʁɛ/",
  "radiodiffuseraient": "/ʁadjɔdifyzəʁɛ/",
  "radiodiffuserais": "/ʁadjɔdifyzəʁɛ/",
  "radiodiffuserait": "/ʁadjɔdifyzəʁɛ/",
  "radiodiffuseras": "/ʁadjɔdifyzəʁa/",
  "radiodiffusèrent": "/ʁadjɔdifyzɛʁ/",
  "radiodiffuserez": "/ʁadjɔdifyzəʁe/",
  "radiodiffuseriez": "/ʁadjɔdifyzəʁje/",
  "radiodiffuserions": "/ʁadjɔdifyzəʁjɔ̃/",
  "radiodiffuserons": "/ʁadjɔdifyzəʁɔ̃/",
  "radiodiffuseront": "/ʁadjɔdifyzəʁɔ̃/",
  "radiodiffuses": "/ʁadjɔdifyz/",
  "radiodiffusés": "/ʁadjɔdifyze/",
  "radiodiffusez": "/ʁadjɔdifyze/",
  "radiodiffusiez": "/ʁadjɔdifyzje/",
  "radiodiffusion": "/ʁadjɔdifyzjɔ̃/",
  "radiodiffusions": "/ʁadjɔdifyzjɔ̃/",
  "radiodiffusons": "/ʁadjɔdifyzɔ̃/",
  "radioélectricien": "/ʁadjɔelɛktʁisjɛ̃/",
  "radioélectricienne": "/ʁadjɔelɛktʁisjɛn/",
  "radioélectrique": "/ʁadjɔelɛktʁik/",
  "radioélectriques": "/ʁadjɔelɛktʁik/",
  "radiofréquence": "/ʁadjɔfʁekɑ̃s/",
  "radiogénique": "/ʁadjɔʒenik/",
  "radiographia": "/ʁadjɔgʁafja/",
  "radiographiai": "/ʁadjɔgʁafjɛ/",
  "radiographiaient": "/ʁadjɔgʁafjɛ/",
  "radiographiais": "/ʁadjɔgʁafjɛ/",
  "radiographiait": "/ʁadjɔgʁafjɛ/",
  "radiographiâmes": "/ʁadjɔgʁafjam/",
  "radiographiant": "/ʁadjɔgʁafjɑ̃/",
  "radiographias": "/ʁadjɔgʁafja/",
  "radiographiasse": "/ʁadjɔgʁafjas/",
  "radiographiassent": "/ʁadjɔgʁafjas/",
  "radiographiasses": "/ʁadjɔgʁafjas/",
  "radiographiassiez": "/ʁadjɔgʁafjasje/",
  "radiographiassions": "/ʁadjɔgʁafjasjɔ̃/",
  "radiographiât": "/ʁadjɔgʁafja/",
  "radiographiâtes": "/ʁadjɔgʁafjat/",
  "radiographie": "/ʁadjɔgʁafi/",
  "radiographié": "/ʁadjɔgʁafje/",
  "radiographiée": "/ʁadjɔgʁafje/",
  "radiographiées": "/ʁadjɔgʁafje/",
  "radiographient": "/ʁadjɔgʁafi/",
  "radiographier": "/ʁadjɔgʁafje/",
  "radiographiera": "/ʁadjɔgʁafjəʁa/",
  "radiographierai": "/ʁadjɔgʁafjəʁɛ/",
  "radiographieraient": "/ʁadjɔgʁafjəʁɛ/",
  "radiographierais": "/ʁadjɔgʁafjəʁɛ/",
  "radiographierait": "/ʁadjɔgʁafjəʁɛ/",
  "radiographieras": "/ʁadjɔgʁafjəʁa/",
  "radiographièrent": "/ʁadjɔgʁafjɛʁ/",
  "radiographierez": "/ʁadjɔgʁafjəʁe/",
  "radiographieriez": "/ʁadjɔgʁafjəʁje/",
  "radiographierions": "/ʁadjɔgʁafjəʁjɔ̃/",
  "radiographierons": "/ʁadjɔgʁafjəʁɔ̃/",
  "radiographieront": "/ʁadjɔgʁafjəʁɔ̃/",
  "radiographies": "/ʁadjɔgʁafi/",
  "radiographiés": "/ʁadjɔgʁafje/",
  "radiographiez": "/ʁadjɔgʁafje/",
  "radiographiiez": "/ʁadjɔgʁafije/",
  "radiographiions": "/ʁadjɔgʁafijɔ̃/",
  "radiographions": "/ʁadjɔgʁafjɔ̃/",
  "radiographique": "/ʁadjɔgʁafik/",
  "radioguidage": "/ʁadjɔgidaʒ/",
  "radioguidages": "/ʁadjɔgidaʒ/",
  "radioguidé": "/ʁadjɔgide/",
  "radioguidée": "/ʁadjɔgide/",
  "radioguidées": "/ʁadjɔgide/",
  "radioguidés": "/ʁadjɔgide/",
  "radiologie": "/ʁadjɔlɔʒi/",
  "radiologies": "/ʁadjɔlɔʒi/",
  "radiologique": "/ʁadjɔlɔʒik/",
  "radiologiques": "/ʁadjɔlɔʒik/",
  "radiologiste": "/ʁadjɔlɔʒist/",
  "radiologistes": "/ʁadjɔlɔʒist/",
  "radioluminescence": "/ʁadjɔlyminɛsɑ̃s/",
  "radionavigation": "/ʁadjɔnavigasjɔ̃/",
  "radionavigations": "/ʁadjɔnavigasjɔ̃/",
  "radions": "/ʁadjɔ̃/",
  "radiophare": "/ʁadjɔfaʁ/",
  "radiophares": "/ʁadjɔfaʁ/",
  "radiophonie": "/ʁadjɔfɔni/",
  "radiophonies": "/ʁadjɔfɔni/",
  "radiophonique": "/ʁadjɔfɔnik/",
  "radiophoniques": "/ʁadjɔfɔnik/",
  "radioreportage": "/ʁadjɔʁəpɔʁtaʒ/",
  "radioreportages": "/ʁadjɔʁəpɔʁtaʒ/",
  "radioreporter": "/ʁadjɔʁəpɔʁtɛʁ/",
  "radioreporters": "/ʁadjɔʁəpɔʁtɛʁ/",
  "radioréveil": "/ʁadjɔʁevɛj/",
  "radios": "/ʁadjo/",
  "radioscopie": "/ʁadjɔskɔpi/",
  "radioscopies": "/ʁadjɔskɔpi/",
  "radioscopique": "/ʁadjɔskɔpik/",
  "radiosondage": "/ʁadjɔsɔ̃daʒ/",
  "radiosondages": "/ʁadjɔsɔ̃daʒ/",
  "radiosonde": "/ʁadjɔsɔ̃d/",
  "radiosondes": "/ʁadjɔsɔ̃d/",
  "radiotechnique": "/ʁadjɔtɛknik/",
  "radiotechniques": "/ʁadjɔtɛknik/",
  "radiotélégramme": "/ʁadjɔtelegʁam/",
  "radiotéléphone": "/ʁadjɔtelefɔn/",
  "radiotéléphones": "/ʁadjɔtelefɔn/",
  "radiotélescope": "/ʁadjɔteleskɔp/",
  "radiotélescopes": "/ʁadjɔteleskɔp/",
  "radiotélévisé": "/ʁadjɔtelevize/",
  "radiotélévisée": "/ʁadjɔtelevize/",
  "radiotélévisées": "/ʁadjɔtelevize/",
  "radiotélévisés": "/ʁadjɔtelevize/",
  "radiotélévision": "/ʁadjɔtelevizjɔ̃/",
  "radiothérapie": "/ʁadjɔteʁapi/",
  "radiothérapies": "/ʁadjɔteʁapi/",
  "radis": "/ʁadi/",
  "radium": "/ʁadjɔm/",
  "radiums": "/ʁadjɔm/",
  "radius": "/ʁadjys/",
  "radjah": "/ʁadʒa/",
  "radjahs": "/ʁadʒa/",
  "radôme": "/ʁadom/",
  "radômes": "/ʁadom/",
  "radota": "/ʁadɔta/",
  "radotage": "/ʁadɔtaʒ/",
  "radotages": "/ʁadɔtaʒ/",
  "radotai": "/ʁadɔtɛ/",
  "radotaient": "/ʁadɔtɛ/",
  "radotais": "/ʁadɔtɛ/",
  "radotait": "/ʁadɔtɛ/",
  "radotâmes": "/ʁadɔtam/",
  "radotant": "/ʁadɔtɑ̃/",
  "radotas": "/ʁadɔta/",
  "radotasse": "/ʁadɔtas/",
  "radotassent": "/ʁadɔtas/",
  "radotasses": "/ʁadɔtas/",
  "radotassiez": "/ʁadɔtasje/",
  "radotassions": "/ʁadɔtasjɔ̃/",
  "radotât": "/ʁadɔta/",
  "radotâtes": "/ʁadɔtat/",
  "radote": "/ʁadɔt/",
  "radoté": "/ʁadɔte/",
  "radotée": "/ʁadɔte/",
  "radotées": "/ʁadɔte/",
  "radotent": "/ʁadɔt/",
  "radoter": "/ʁadɔte/",
  "radotera": "/ʁadɔtəʁa/",
  "radoterai": "/ʁadɔtəʁɛ/",
  "radoteraient": "/ʁadɔtəʁɛ/",
  "radoterais": "/ʁadɔtəʁɛ/",
  "radoterait": "/ʁadɔtəʁɛ/",
  "radoteras": "/ʁadɔtəʁa/",
  "radotèrent": "/ʁadɔtɛʁ/",
  "radoterez": "/ʁadɔtəʁe/",
  "radoteriez": "/ʁadɔtəʁje/",
  "radoterions": "/ʁadɔtəʁjɔ̃/",
  "radoterons": "/ʁadɔtəʁɔ̃/",
  "radoteront": "/ʁadɔtəʁɔ̃/",
  "radotes": "/ʁadɔt/",
  "radotés": "/ʁadɔte/",
  "radoteur": "/ʁadɔtœʁ/",
  "radoteurs": "/ʁadɔtœʁ/",
  "radoteuse": "/ʁadɔtøz/",
  "radoteuses": "/ʁadɔtøz/",
  "radotez": "/ʁadɔte/",
  "radotiez": "/ʁadɔtje/",
  "radotions": "/ʁadɔtjɔ̃/",
  "radotons": "/ʁadɔtɔ̃/",
  "radoub": "/ʁadu/",
  "radouba": "/ʁaduba/",
  "radoubai": "/ʁadubɛ/",
  "radoubaient": "/ʁadubɛ/",
  "radoubais": "/ʁadubɛ/",
  "radoubait": "/ʁadubɛ/",
  "radoubâmes": "/ʁadubam/",
  "radoubant": "/ʁadubɑ̃/",
  "radoubas": "/ʁaduba/",
  "radoubasse": "/ʁadubas/",
  "radoubassent": "/ʁadubas/",
  "radoubasses": "/ʁadubas/",
  "radoubassiez": "/ʁadubasje/",
  "radoubassions": "/ʁadubasjɔ̃/",
  "radoubât": "/ʁaduba/",
  "radoubâtes": "/ʁadubat/",
  "radoube": "/ʁadub/",
  "radoubé": "/ʁadube/",
  "radoubée": "/ʁadube/",
  "radoubées": "/ʁadube/",
  "radoubent": "/ʁadub/",
  "radouber": "/ʁadube/",
  "radoubera": "/ʁadubəʁa/",
  "radouberai": "/ʁadubəʁɛ/",
  "radouberaient": "/ʁadubəʁɛ/",
  "radouberais": "/ʁadubəʁɛ/",
  "radouberait": "/ʁadubəʁɛ/",
  "radouberas": "/ʁadubəʁa/",
  "radoubèrent": "/ʁadubɛʁ/",
  "radouberez": "/ʁadubəʁe/",
  "radouberiez": "/ʁadubəʁje/",
  "radouberions": "/ʁadubəʁjɔ̃/",
  "radouberons": "/ʁadubəʁɔ̃/",
  "radouberont": "/ʁadubəʁɔ̃/",
  "radoubes": "/ʁadub/",
  "radoubés": "/ʁadube/",
  "radoubez": "/ʁadube/",
  "radoubiez": "/ʁadubje/",
  "radoubions": "/ʁadubjɔ̃/",
  "radoubons": "/ʁadubɔ̃/",
  "radoubs": "/ʁadu/",
  "radouci": "/ʁadusi/",
  "radoucie": "/ʁadusi/",
  "radoucies": "/ʁadusi/",
  "radoucîmes": "/ʁadusim/",
  "radoucir": "/ʁadusiʁ/",
  "radoucira": "/ʁadusiʁa/",
  "radoucirai": "/ʁadusiʁɛ/",
  "radouciraient": "/ʁadusiʁɛ/",
  "radoucirais": "/ʁadusiʁɛ/",
  "radoucirait": "/ʁadusiʁɛ/",
  "radouciras": "/ʁadusiʁa/",
  "radoucirent": "/ʁadusiʁ/",
  "radoucirez": "/ʁadusiʁe/",
  "radouciriez": "/ʁadusiʁje/",
  "radoucirions": "/ʁadusiʁjɔ̃/",
  "radoucirons": "/ʁadusiʁɔ̃/",
  "radouciront": "/ʁadusiʁɔ̃/",
  "radoucis": "/ʁadusi/",
  "radoucissaient": "/ʁadusisɛ/",
  "radoucissais": "/ʁadusisɛ/",
  "radoucissait": "/ʁadusisɛ/",
  "radoucissant": "/ʁadusisɑ̃/",
  "radoucisse": "/ʁadusis/",
  "radoucissement": "/ʁadusismɑ̃/",
  "radoucissements": "/ʁadusismɑ̃/",
  "radoucissent": "/ʁadusis/",
  "radoucisses": "/ʁadusis/",
  "radoucissez": "/ʁadusise/",
  "radoucissiez": "/ʁadusisje/",
  "radoucissions": "/ʁadusisjɔ̃/",
  "radoucissons": "/ʁadusisɔ̃/",
  "radoucit": "/ʁadusi/",
  "radoucît": "/ʁadusi/",
  "radoucîtes": "/ʁadusit/"
}