{
  "sabayon": "/sabajɔ̃/",
  "sabayons": "/sabajɔ̃/",
  "sabbat": "/saba/",
  "sabbatique": "/sabatik/",
  "sabbatiques": "/sabatik/",
  "sabbats": "/saba/",
  "Sabin": "/sabɛ̃/",
  "Sabine": "/sabin/",
  "sabir": "/sabiʁ/",
  "sabirs": "/sabiʁ/",
  "sabla": "/sabla/",
  "sablage": "/sablaʒ/",
  "sablages": "/sablaʒ/",
  "sablai": "/sablɛ/",
  "sablaient": "/sablɛ/",
  "sablais": "/sablɛ/",
  "sablait": "/sablɛ/",
  "sablâmes": "/sablam/",
  "sablant": "/sablɑ̃/",
  "sablas": "/sabla/",
  "sablasse": "/sablas/",
  "sablassent": "/sablas/",
  "sablasses": "/sablas/",
  "sablassiez": "/sablasje/",
  "sablassions": "/sablasjɔ̃/",
  "sablât": "/sabla/",
  "sablâtes": "/sablat/",
  "sable": "/sabl/",
  "sablé": "/sable/",
  "sablée": "/sable/",
  "sablées": "/sable/",
  "sablent": "/sabl/",
  "sabler": "/sable/",
  "sablera": "/sabləʁa/",
  "sablerai": "/sabləʁɛ/",
  "sableraient": "/sabləʁɛ/",
  "sablerais": "/sabləʁɛ/",
  "sablerait": "/sabləʁɛ/",
  "sableras": "/sabləʁa/",
  "sablèrent": "/sablɛʁ/",
  "sablerez": "/sabləʁe/",
  "sableriez": "/sabləʁje/",
  "sablerions": "/sabləʁjɔ̃/",
  "sablerons": "/sabləʁɔ̃/",
  "sableront": "/sabləʁɔ̃/",
  "sables": "/sabl/",
  "sablés": "/sable/",
  "sableur": "/sablœʁ/",
  "sableurs": "/sablœʁ/",
  "sableuse": "/sabløz/",
  "sableuses": "/sabløz/",
  "sableux": "/sablø/",
  "sablez": "/sable/",
  "sablier": "/sablije/",
  "sablière": "/sablijɛʁ/",
  "sablières": "/sablijɛʁ/",
  "sabliers": "/sablije/",
  "sabliez": "/sablje/",
  "sablions": "/sabljɔ̃/",
  "sablonneuse": "/sablɔnøz/",
  "sablonneuses": "/sablɔnøz/",
  "sablonneux": "/sablɔnø/",
  "sablonnière": "/sablɔnjɛʁ/",
  "sablonnières": "/sablɔnjɛʁ/",
  "sablons": "/sablɔ̃/",
  "sabord": "/sabɔʁ/",
  "saborda": "/sabɔʁda/",
  "sabordage": "/sabɔʁdaʒ/",
  "sabordages": "/sabɔʁdaʒ/",
  "sabordai": "/sabɔʁdɛ/",
  "sabordaient": "/sabɔʁdɛ/",
  "sabordais": "/sabɔʁdɛ/",
  "sabordait": "/sabɔʁdɛ/",
  "sabordâmes": "/sabɔʁdam/",
  "sabordant": "/sabɔʁdɑ̃/",
  "sabordas": "/sabɔʁda/",
  "sabordasse": "/sabɔʁdas/",
  "sabordassent": "/sabɔʁdas/",
  "sabordasses": "/sabɔʁdas/",
  "sabordassiez": "/sabɔʁdasje/",
  "sabordassions": "/sabɔʁdasjɔ̃/",
  "sabordât": "/sabɔʁda/",
  "sabordâtes": "/sabɔʁdat/",
  "saborde": "/sabɔʁd/",
  "sabordé": "/sabɔʁde/",
  "sabordée": "/sabɔʁde/",
  "sabordées": "/sabɔʁde/",
  "sabordent": "/sabɔʁd/",
  "saborder": "/sabɔʁde/",
  "sabordera": "/sabɔʁdəʁa/",
  "saborderai": "/sabɔʁdəʁɛ/",
  "saborderaient": "/sabɔʁdəʁɛ/",
  "saborderais": "/sabɔʁdəʁɛ/",
  "saborderait": "/sabɔʁdəʁɛ/",
  "saborderas": "/sabɔʁdəʁa/",
  "sabordèrent": "/sabɔʁdɛʁ/",
  "saborderez": "/sabɔʁdəʁe/",
  "saborderiez": "/sabɔʁdəʁje/",
  "saborderions": "/sabɔʁdəʁjɔ̃/",
  "saborderons": "/sabɔʁdəʁɔ̃/",
  "saborderont": "/sabɔʁdəʁɔ̃/",
  "sabordes": "/sabɔʁd/",
  "sabordés": "/sabɔʁde/",
  "sabordez": "/sabɔʁde/",
  "sabordiez": "/sabɔʁdje/",
  "sabordions": "/sabɔʁdjɔ̃/",
  "sabordons": "/sabɔʁdɔ̃/",
  "sabords": "/sabɔʁ/",
  "sabot": "/sabo/",
  "sabota": "/sabɔta/",
  "sabotage": "/sabɔtaʒ/",
  "sabotages": "/sabɔtaʒ/",
  "sabotai": "/sabɔtɛ/",
  "sabotaient": "/sabɔtɛ/",
  "sabotais": "/sabɔtɛ/",
  "sabotait": "/sabɔtɛ/",
  "sabotâmes": "/sabɔtam/",
  "sabotant": "/sabɔtɑ̃/",
  "sabotas": "/sabɔta/",
  "sabotasse": "/sabɔtas/",
  "sabotassent": "/sabɔtas/",
  "sabotasses": "/sabɔtas/",
  "sabotassiez": "/sabɔtasje/",
  "sabotassions": "/sabɔtasjɔ̃/",
  "sabotât": "/sabɔta/",
  "sabotâtes": "/sabɔtat/",
  "sabote": "/sabɔt/",
  "saboté": "/sabɔte/",
  "sabotée": "/sabɔte/",
  "sabotées": "/sabɔte/",
  "sabotent": "/sabɔt/",
  "saboter": "/sabɔte/",
  "sabotera": "/sabɔtəʁa/",
  "saboterai": "/sabɔtəʁɛ/",
  "saboteraient": "/sabɔtəʁɛ/",
  "saboterais": "/sabɔtəʁɛ/",
  "saboterait": "/sabɔtəʁɛ/",
  "saboteras": "/sabɔtəʁa/",
  "sabotèrent": "/sabɔtɛʁ/",
  "saboterez": "/sabɔtəʁe/",
  "saboteriez": "/sabɔtəʁje/",
  "saboterions": "/sabɔtəʁjɔ̃/",
  "saboterons": "/sabɔtəʁɔ̃/",
  "saboteront": "/sabɔtəʁɔ̃/",
  "sabotes": "/sabɔt/",
  "sabotés": "/sabɔte/",
  "saboteur": "/sabɔtœʁ/",
  "saboteurs": "/sabɔtœʁ/",
  "saboteuse": "/sabɔtøz/",
  "saboteuses": "/sabɔtøz/",
  "sabotez": "/sabɔte/",
  "sabotier": "/sabɔtje/",
  "sabotière": "/sabɔtjɛʁ/",
  "sabotières": "/sabɔtjɛʁ/",
  "sabotiers": "/sabɔtje/",
  "sabotiez": "/sabɔtje/",
  "sabotions": "/sabɔtjɔ̃/",
  "sabotons": "/sabɔtɔ̃/",
  "sabots": "/sabo/",
  "sabra": "/sabʁa/",
  "sabrai": "/sabʁɛ/",
  "sabraient": "/sabʁɛ/",
  "sabrais": "/sabʁɛ/",
  "sabrait": "/sabʁɛ/",
  "sabrâmes": "/sabʁam/",
  "sabrant": "/sabʁɑ̃/",
  "sabras": "/sabʁa/",
  "sabrasse": "/sabʁas/",
  "sabrassent": "/sabʁas/",
  "sabrasses": "/sabʁas/",
  "sabrassiez": "/sabʁasje/",
  "sabrassions": "/sabʁasjɔ̃/",
  "sabrât": "/sabʁa/",
  "sabrâtes": "/sabʁat/",
  "sabre": "/sabʁ/",
  "sabré": "/sabʁe/",
  "sabrée": "/sabʁe/",
  "sabrées": "/sabʁe/",
  "sabrent": "/sabʁ/",
  "sabrer": "/sabʁe/",
  "sabrera": "/sabʁəʁa/",
  "sabrerai": "/sabʁəʁɛ/",
  "sabreraient": "/sabʁəʁɛ/",
  "sabrerais": "/sabʁəʁɛ/",
  "sabrerait": "/sabʁəʁɛ/",
  "sabreras": "/sabʁəʁa/",
  "sabrèrent": "/sabʁɛʁ/",
  "sabrerez": "/sabʁəʁe/",
  "sabreriez": "/sabʁəʁje/",
  "sabrerions": "/sabʁəʁjɔ̃/",
  "sabrerons": "/sabʁəʁɔ̃/",
  "sabreront": "/sabʁəʁɔ̃/",
  "sabres": "/sabʁ/",
  "sabrés": "/sabʁe/",
  "sabreur": "/sabʁœʁ/",
  "sabreurs": "/sabʁœʁ/",
  "sabreuse": "/sabʁøz/",
  "sabreuses": "/sabʁøz/",
  "sabrez": "/sabʁe/",
  "sabriez": "/sabʁje/",
  "sabrions": "/sabʁjɔ̃/",
  "sabrons": "/sabʁɔ̃/"
}