{
  "tînmes": "/tɛ̃m/",
  "tinrent": "/tɛ̃ʁ/",
  "tins": "/tɛ̃/",
  "tinsse": "/tɛ̃s/",
  "tinssent": "/tɛ̃s/",
  "tinsses": "/tɛ̃s/",
  "tinssiez": "/tɛ̃sje/",
  "tinssions": "/tɛ̃sjɔ̃/",
  "tint": "/tɛ̃/",
  "tînt": "/tɛ̃/",
  "tinta": "/tɛ̃ta/",
  "tintai": "/tɛ̃tɛ/",
  "tintaient": "/tɛ̃tɛ/",
  "tintais": "/tɛ̃tɛ/",
  "tintait": "/tɛ̃tɛ/",
  "tintamarre": "/tɛ̃tamaʁ/",
  "tintamarres": "/tɛ̃tamaʁ/",
  "tintâmes": "/tɛ̃tam/",
  "tintant": "/tɛ̃tɑ̃/",
  "tintas": "/tɛ̃ta/",
  "tintasse": "/tɛ̃tas/",
  "tintassent": "/tɛ̃tas/",
  "tintasses": "/tɛ̃tas/",
  "tintassiez": "/tɛ̃tasje/",
  "tintassions": "/tɛ̃tasjɔ̃/",
  "tintât": "/tɛ̃ta/",
  "tintâtes": "/tɛ̃tat/",
  "tinte": "/tɛ̃t/",
  "tinté": "/tɛ̃te/",
  "tintée": "/tɛ̃te/",
  "tintées": "/tɛ̃te/",
  "tintement": "/tɛ̃tmɑ̃/",
  "tintements": "/tɛ̃tmɑ̃/",
  "tintent": "/tɛ̃t/",
  "tinter": "/tɛ̃te/",
  "tintera": "/tɛ̃təʁa/",
  "tinterai": "/tɛ̃təʁɛ/",
  "tinteraient": "/tɛ̃təʁɛ/",
  "tinterais": "/tɛ̃təʁɛ/",
  "tinterait": "/tɛ̃təʁɛ/",
  "tinteras": "/tɛ̃təʁa/",
  "tintèrent": "/tɛ̃tɛʁ/",
  "tinterez": "/tɛ̃təʁe/",
  "tinteriez": "/tɛ̃təʁje/",
  "tinterions": "/tɛ̃təʁjɔ̃/",
  "tinterons": "/tɛ̃təʁɔ̃/",
  "tinteront": "/tɛ̃təʁɔ̃/",
  "tintes": "/tɛ̃t/",
  "tîntes": "/tɛ̃t/",
  "tintés": "/tɛ̃te/",
  "tintez": "/tɛ̃te/",
  "tintiez": "/tɛ̃tje/",
  "tintin": "/tɛ̃tɛ̃/",
  "tintins": "/tɛ̃tɛ̃/",
  "tintions": "/tɛ̃tjɔ̃/",
  "tintons": "/tɛ̃tɔ̃/",
  "Tintoret": "/tɛ̃tɔʁɛ/",
  "tintouin": "/tɛ̃twɛ̃/",
  "tintouins": "/tɛ̃twɛ̃/"
}